{
"meta":{"test_sets":[],"test_metrics":[],"learn_metrics":[{"best_value":"Min","name":"RMSE"}],"launch_mode":"Train","parameters":"","iteration_count":1000,"learn_sets":["learn"],"name":"experiment"},
"iterations":[
{"learn":[43.43374045],"iteration":0,"passed_time":0.05853419414,"remaining_time":58.47565994},
{"learn":[42.76696671],"iteration":1,"passed_time":0.05942037257,"remaining_time":29.65076591},
{"learn":[42.07863228],"iteration":2,"passed_time":0.06023813344,"remaining_time":20.01913968},
{"learn":[41.41600725],"iteration":3,"passed_time":0.06105076923,"remaining_time":15.20164154},
{"learn":[40.87411868],"iteration":4,"passed_time":0.06190490557,"remaining_time":12.31907621},
{"learn":[40.3762567],"iteration":5,"passed_time":0.06270637455,"remaining_time":10.38835605},
{"learn":[39.86723029],"iteration":6,"passed_time":0.06356613597,"remaining_time":9.017310432},
{"learn":[39.30726135],"iteration":7,"passed_time":0.06432768775,"remaining_time":7.976633282},
{"learn":[38.77908274],"iteration":8,"passed_time":0.06517682403,"remaining_time":7.176692513},
{"learn":[38.31332389],"iteration":9,"passed_time":0.06598508477,"remaining_time":6.532523392},
{"learn":[37.82135938],"iteration":10,"passed_time":0.06677755363,"remaining_time":6.00390914},
{"learn":[37.4962046],"iteration":11,"passed_time":0.06753735539,"remaining_time":5.560575594},
{"learn":[37.11599432],"iteration":12,"passed_time":0.06832482418,"remaining_time":5.187430882},
{"learn":[36.6418878],"iteration":13,"passed_time":0.06907033408,"remaining_time":4.864524957},
{"learn":[36.3460688],"iteration":14,"passed_time":0.06979413536,"remaining_time":4.583148222},
{"learn":[36.03465404],"iteration":15,"passed_time":0.07063693822,"remaining_time":4.344171701},
{"learn":[35.81839326],"iteration":16,"passed_time":0.07161257618,"remaining_time":4.140891905},
{"learn":[35.4826236],"iteration":17,"passed_time":0.07234887763,"remaining_time":3.947033213},
{"learn":[35.18028384],"iteration":18,"passed_time":0.07317001353,"remaining_time":3.77788333},
{"learn":[34.86369357],"iteration":19,"passed_time":0.07390598164,"remaining_time":3.621393101},
{"learn":[34.57143612],"iteration":20,"passed_time":0.0747035339,"remaining_time":3.482607604},
{"learn":[34.38492352],"iteration":21,"passed_time":0.07548129423,"remaining_time":3.355486625},
{"learn":[34.18392894],"iteration":22,"passed_time":0.07633418056,"remaining_time":3.242543235},
{"learn":[34.02377503],"iteration":23,"passed_time":0.07714985806,"remaining_time":3.137427561},
{"learn":[33.80728175],"iteration":24,"passed_time":0.07792953509,"remaining_time":3.039251868},
{"learn":[33.56809058],"iteration":25,"passed_time":0.0789622988,"remaining_time":2.958049194},
{"learn":[33.39721333],"iteration":26,"passed_time":0.0798175185,"remaining_time":2.87638687},
{"learn":[33.18810607],"iteration":27,"passed_time":0.08066165471,"remaining_time":2.800111728},
{"learn":[32.98458835],"iteration":28,"passed_time":0.08138699768,"remaining_time":2.725061198},
{"learn":[32.8085491],"iteration":29,"passed_time":0.08265743122,"remaining_time":2.672590276},
{"learn":[32.6286832],"iteration":30,"passed_time":0.08352160936,"remaining_time":2.610723854},
{"learn":[32.41729835],"iteration":31,"passed_time":0.08470379173,"remaining_time":2.5622897},
{"learn":[32.21496376],"iteration":32,"passed_time":0.08541334282,"remaining_time":2.502869773},
{"learn":[32.06854262],"iteration":33,"passed_time":0.08636160542,"remaining_time":2.453685613},
{"learn":[31.94716566],"iteration":34,"passed_time":0.08744841152,"remaining_time":2.411077632},
{"learn":[31.82208567],"iteration":35,"passed_time":0.0887745958,"remaining_time":2.377186399},
{"learn":[31.61767552],"iteration":36,"passed_time":0.08946718833,"remaining_time":2.328564929},
{"learn":[31.46672343],"iteration":37,"passed_time":0.0901250304,"remaining_time":2.281586296},
{"learn":[31.31235288],"iteration":38,"passed_time":0.0909455413,"remaining_time":2.240991415},
{"learn":[31.15360416],"iteration":39,"passed_time":0.09164384224,"remaining_time":2.199452214},
{"learn":[31.05109797],"iteration":40,"passed_time":0.09234164318,"remaining_time":2.159893556},
{"learn":[30.88043953],"iteration":41,"passed_time":0.09311211175,"remaining_time":2.12384293},
{"learn":[30.75636746],"iteration":42,"passed_time":0.0938518299,"remaining_time":2.088748866},
{"learn":[30.64092197],"iteration":43,"passed_time":0.09454738081,"remaining_time":2.054256728},
{"learn":[30.52601149],"iteration":44,"passed_time":0.09525843192,"remaining_time":2.021595611},
{"learn":[30.38751035],"iteration":45,"passed_time":0.09597077472,"remaining_time":1.990350415},
{"learn":[30.29665329],"iteration":46,"passed_time":0.09666682563,"remaining_time":1.960074145},
{"learn":[30.18901875],"iteration":47,"passed_time":0.09739391862,"remaining_time":1.931646053},
{"learn":[30.04411605],"iteration":48,"passed_time":0.09821255449,"remaining_time":1.906125292},
{"learn":[29.98705617],"iteration":49,"passed_time":0.09902323193,"remaining_time":1.881441407},
{"learn":[29.87043528],"iteration":50,"passed_time":0.0997894921,"remaining_time":1.856867216},
{"learn":[29.78321984],"iteration":51,"passed_time":0.1004988765,"remaining_time":1.832171826},
{"learn":[29.64286823],"iteration":52,"passed_time":0.1013154707,"remaining_time":1.810297184},
{"learn":[29.54740308],"iteration":53,"passed_time":0.1022354413,"remaining_time":1.791013471},
{"learn":[29.408843],"iteration":54,"passed_time":0.103072119,"remaining_time":1.770966409},
{"learn":[29.2782241],"iteration":55,"passed_time":0.1037763367,"remaining_time":1.749372533},
{"learn":[29.12821563],"iteration":56,"passed_time":0.1045779307,"remaining_time":1.730122608},
{"learn":[28.99383815],"iteration":57,"passed_time":0.1053933582,"remaining_time":1.711733507},
{"learn":[28.88606171],"iteration":58,"passed_time":0.1062246609,"remaining_time":1.694193321},
{"learn":[28.7699304],"iteration":59,"passed_time":0.1069256702,"remaining_time":1.675168833},
{"learn":[28.57517648],"iteration":60,"passed_time":0.1075976375,"remaining_time":1.656298059},
{"learn":[28.46610495],"iteration":61,"passed_time":0.1082375626,"remaining_time":1.637529577},
{"learn":[28.36282531],"iteration":62,"passed_time":0.1088963631,"remaining_time":1.619617336},
{"learn":[28.28560752],"iteration":63,"passed_time":0.1099717107,"remaining_time":1.608336269},
{"learn":[28.21853338],"iteration":64,"passed_time":0.1108257637,"remaining_time":1.594185985},
{"learn":[28.08375708],"iteration":65,"passed_time":0.1116681499,"remaining_time":1.580273515},
{"learn":[27.99631843],"iteration":66,"passed_time":0.1124150765,"remaining_time":1.565421886},
{"learn":[27.92855744],"iteration":67,"passed_time":0.1131888784,"remaining_time":1.551353451},
{"learn":[27.88078548],"iteration":68,"passed_time":0.1140251812,"remaining_time":1.538513677},
{"learn":[27.80698942],"iteration":69,"passed_time":0.1150764868,"remaining_time":1.528873325},
{"learn":[27.74006576],"iteration":70,"passed_time":0.1164323798,"remaining_time":1.523460294},
{"learn":[27.66062033],"iteration":71,"passed_time":0.1175440196,"remaining_time":1.515011808},
{"learn":[27.55664256],"iteration":72,"passed_time":0.1185156992,"remaining_time":1.504987029},
{"learn":[27.48734561],"iteration":73,"passed_time":0.1195301293,"remaining_time":1.495741888},
{"learn":[27.42470578],"iteration":74,"passed_time":0.1202232635,"remaining_time":1.482753583},
{"learn":[27.33408995],"iteration":75,"passed_time":0.1209527315,"remaining_time":1.470530578},
{"learn":[27.24306318],"iteration":76,"passed_time":0.1216640743,"remaining_time":1.458388839},
{"learn":[27.15450451],"iteration":77,"passed_time":0.1223427917,"remaining_time":1.446154537},
{"learn":[27.12949277],"iteration":78,"passed_time":0.1230440926,"remaining_time":1.434476067},
{"learn":[26.978663],"iteration":79,"passed_time":0.1237713523,"remaining_time":1.423370552},
{"learn":[26.88482247],"iteration":80,"passed_time":0.1245818631,"remaining_time":1.413465829},
{"learn":[26.83065307],"iteration":81,"passed_time":0.1255134171,"remaining_time":1.405138011},
{"learn":[26.75073479],"iteration":82,"passed_time":0.1265368057,"remaining_time":1.398003022},
{"learn":[26.67350826],"iteration":83,"passed_time":0.1273638584,"remaining_time":1.388872551},
{"learn":[26.57261082],"iteration":84,"passed_time":0.1281387436,"remaining_time":1.379375888},
{"learn":[26.50973741],"iteration":85,"passed_time":0.1289622963,"remaining_time":1.370599288},
{"learn":[26.42374668],"iteration":86,"passed_time":0.1298915169,"remaining_time":1.363114425},
{"learn":[26.365186],"iteration":87,"passed_time":0.1305884012,"remaining_time":1.353370703},
{"learn":[26.25136701],"iteration":88,"passed_time":0.1313062441,"remaining_time":1.344044813},
{"learn":[26.1913224],"iteration":89,"passed_time":0.1319624611,"remaining_time":1.334287107},
{"learn":[26.03652086],"iteration":90,"passed_time":0.1326373034,"remaining_time":1.324915481},
{"learn":[25.98720082],"iteration":91,"passed_time":0.1332752285,"remaining_time":1.31536856},
{"learn":[25.90074405],"iteration":92,"passed_time":0.1340254052,"remaining_time":1.307107984},
{"learn":[25.7771914],"iteration":93,"passed_time":0.1347304979,"remaining_time":1.298572671},
{"learn":[25.72904317],"iteration":94,"passed_time":0.1354210904,"remaining_time":1.290064071},
{"learn":[25.62812136],"iteration":95,"passed_time":0.1362045591,"remaining_time":1.282592932},
{"learn":[25.59321434],"iteration":96,"passed_time":0.1369784861,"remaining_time":1.275170855},
{"learn":[25.5326946],"iteration":97,"passed_time":0.1377062874,"remaining_time":1.267459911},
{"learn":[25.49086554],"iteration":98,"passed_time":0.1384209219,"remaining_time":1.259770208},
{"learn":[25.35923978],"iteration":99,"passed_time":0.1391788903,"remaining_time":1.252610013},
{"learn":[25.31361619],"iteration":100,"passed_time":0.1400819023,"remaining_time":1.246867625},
{"learn":[25.22566764],"iteration":101,"passed_time":0.1407874533,"remaining_time":1.239481697},
{"learn":[25.14155633],"iteration":102,"passed_time":0.1415770471,"remaining_time":1.232957391},
{"learn":[25.03587014],"iteration":103,"passed_time":0.1423738077,"remaining_time":1.226605113},
{"learn":[24.98418047],"iteration":104,"passed_time":0.143295945,"remaining_time":1.22142734},
{"learn":[24.87882686],"iteration":105,"passed_time":0.1441706233,"remaining_time":1.215929596},
{"learn":[24.77213495],"iteration":106,"passed_time":0.1451892201,"remaining_time":1.211719379},
{"learn":[24.71570969],"iteration":107,"passed_time":0.1462175671,"remaining_time":1.207648795},
{"learn":[24.60928385],"iteration":108,"passed_time":0.1474498335,"remaining_time":1.205300932},
{"learn":[24.56364014],"iteration":109,"passed_time":0.1485220561,"remaining_time":1.201678454},
{"learn":[24.54371107],"iteration":110,"passed_time":0.149393401,"remaining_time":1.196493094},
{"learn":[24.42691864],"iteration":111,"passed_time":0.1504808321,"remaining_time":1.193098026},
{"learn":[24.35978405],"iteration":112,"passed_time":0.1514000109,"remaining_time":1.188423095},
{"learn":[24.28942577],"iteration":113,"passed_time":0.1526085687,"remaining_time":1.186063086},
{"learn":[24.24145342],"iteration":114,"passed_time":0.1539316279,"remaining_time":1.184604267},
{"learn":[24.16992371],"iteration":115,"passed_time":0.1547362219,"remaining_time":1.179196726},
{"learn":[24.13215214],"iteration":116,"passed_time":0.1554817735,"remaining_time":1.173422273},
{"learn":[24.07227818],"iteration":117,"passed_time":0.1566057468,"remaining_time":1.170561599},
{"learn":[24.02090774],"iteration":118,"passed_time":0.1572640888,"remaining_time":1.164282876},
{"learn":[23.88482237],"iteration":119,"passed_time":0.1579213476,"remaining_time":1.158089882},
{"learn":[23.79031081],"iteration":120,"passed_time":0.1586490656,"remaining_time":1.152500237},
{"learn":[23.74559261],"iteration":121,"passed_time":0.1593488665,"remaining_time":1.146789384},
{"learn":[23.68319049],"iteration":122,"passed_time":0.1600819179,"remaining_time":1.14139709},
{"learn":[23.65287649],"iteration":123,"passed_time":0.1607799689,"remaining_time":1.135832683},
{"learn":[23.58382477],"iteration":124,"passed_time":0.1615770628,"remaining_time":1.13103944},
{"learn":[23.46193653],"iteration":125,"passed_time":0.1623151976,"remaining_time":1.125900656},
{"learn":[23.38156484],"iteration":126,"passed_time":0.1631137915,"remaining_time":1.121246772},
{"learn":[23.27452881],"iteration":127,"passed_time":0.1639227189,"remaining_time":1.116723523},
{"learn":[23.22228197],"iteration":128,"passed_time":0.1646384784,"remaining_time":1.111628796},
{"learn":[23.17103472],"iteration":129,"passed_time":0.1654081553,"remaining_time":1.10696227},
{"learn":[23.14278041],"iteration":130,"passed_time":0.1661987075,"remaining_time":1.102493716},
{"learn":[23.00656277],"iteration":131,"passed_time":0.1672195961,"remaining_time":1.099595526},
{"learn":[22.91496031],"iteration":132,"passed_time":0.1682461514,"remaining_time":1.096762506},
{"learn":[22.83395576],"iteration":133,"passed_time":0.1690123282,"remaining_time":1.092273703},
{"learn":[22.71918651],"iteration":134,"passed_time":0.1697847551,"remaining_time":1.087880098},
{"learn":[22.70534878],"iteration":135,"passed_time":0.1704978063,"remaining_time":1.083162534},
{"learn":[22.64889583],"iteration":136,"passed_time":0.171382068,"remaining_time":1.079581932},
{"learn":[22.60771237],"iteration":137,"passed_time":0.1721119527,"remaining_time":1.07507611},
{"learn":[22.55346585],"iteration":138,"passed_time":0.1729722141,"remaining_time":1.071432204},
{"learn":[22.46437909],"iteration":139,"passed_time":0.1737165157,"remaining_time":1.067115739},
{"learn":[22.42441498],"iteration":140,"passed_time":0.1745277765,"remaining_time":1.063257872},
{"learn":[22.34015836],"iteration":141,"passed_time":0.1753591625,"remaining_time":1.059564517},
{"learn":[22.25809215],"iteration":142,"passed_time":0.1760217963,"remaining_time":1.054899856},
{"learn":[22.19921946],"iteration":143,"passed_time":0.1768194319,"remaining_time":1.05109329},
{"learn":[22.12402276],"iteration":144,"passed_time":0.1774961909,"remaining_time":1.04661547},
{"learn":[22.06323622],"iteration":145,"passed_time":0.1783078683,"remaining_time":1.042978901},
{"learn":[22.02098511],"iteration":146,"passed_time":0.1789717522,"remaining_time":1.038523161},
{"learn":[21.9267907],"iteration":147,"passed_time":0.1796830949,"remaining_time":1.034391871},
{"learn":[21.86268799],"iteration":148,"passed_time":0.1803528538,"remaining_time":1.030068984},
{"learn":[21.76698875],"iteration":149,"passed_time":0.1811013638,"remaining_time":1.026241061},
{"learn":[21.71219119],"iteration":150,"passed_time":0.1817837478,"remaining_time":1.022082132},
{"learn":[21.64193562],"iteration":151,"passed_time":0.1824712986,"remaining_time":1.017997771},
{"learn":[21.56937646],"iteration":152,"passed_time":0.1831369325,"remaining_time":1.013836482},
{"learn":[21.51202319],"iteration":153,"passed_time":0.1839245263,"remaining_time":1.010390579},
{"learn":[21.37393575],"iteration":154,"passed_time":0.1845900351,"remaining_time":1.006313417},
{"learn":[21.32232225],"iteration":155,"passed_time":0.1852725442,"remaining_time":1.00237197},
{"learn":[21.25705761],"iteration":156,"passed_time":0.1860107623,"remaining_time":0.9987711633},
{"learn":[21.20375669],"iteration":157,"passed_time":0.1867693974,"remaining_time":0.9953153963},
{"learn":[21.131643],"iteration":158,"passed_time":0.1876713677,"remaining_time":0.9926516997},
{"learn":[21.07322379],"iteration":159,"passed_time":0.1887360485,"remaining_time":0.9908642547},
{"learn":[21.02077969],"iteration":160,"passed_time":0.1896005183,"remaining_time":0.9880424527},
{"learn":[20.96409118],"iteration":161,"passed_time":0.1904364878,"remaining_time":0.9850973874},
{"learn":[20.89172252],"iteration":162,"passed_time":0.1911169968,"remaining_time":0.9813799161},
{"learn":[20.81531476],"iteration":163,"passed_time":0.1919268826,"remaining_time":0.9783589868},
{"learn":[20.76858598],"iteration":164,"passed_time":0.1926208085,"remaining_time":0.9747780307},
{"learn":[20.70152436],"iteration":165,"passed_time":0.1933525682,"remaining_time":0.9714219389},
{"learn":[20.65325674],"iteration":166,"passed_time":0.1943149143,"remaining_time":0.9692474467},
{"learn":[20.5768166],"iteration":167,"passed_time":0.1951060915,"remaining_time":0.9662396911},
{"learn":[20.50919429],"iteration":168,"passed_time":0.1962409815,"remaining_time":0.9649482583},
{"learn":[20.43525815],"iteration":169,"passed_time":0.1970930345,"remaining_time":0.9622777568},
{"learn":[20.34631126],"iteration":170,"passed_time":0.1980376304,"remaining_time":0.9600771673},
{"learn":[20.28275512],"iteration":171,"passed_time":0.1988992668,"remaining_time":0.9574918195},
{"learn":[20.20540921],"iteration":172,"passed_time":0.2002011591,"remaining_time":0.9570309746},
{"learn":[20.15725858],"iteration":173,"passed_time":0.2009089185,"remaining_time":0.9537400386},
{"learn":[20.13199401],"iteration":174,"passed_time":0.2016994707,"remaining_time":0.9508689333},
{"learn":[20.0546579],"iteration":175,"passed_time":0.2032366161,"remaining_time":0.9515168846},
{"learn":[19.94458051],"iteration":176,"passed_time":0.2040454185,"remaining_time":0.9487535562},
{"learn":[19.88402679],"iteration":177,"passed_time":0.2047174691,"remaining_time":0.945380672},
{"learn":[19.80345089],"iteration":178,"passed_time":0.2054055199,"remaining_time":0.9421113512},
{"learn":[19.74877466],"iteration":179,"passed_time":0.2061033209,"remaining_time":0.9389151284},
{"learn":[19.69687115],"iteration":180,"passed_time":0.2067984134,"remaining_time":0.9357342575},
{"learn":[19.6459752],"iteration":181,"passed_time":0.2075562152,"remaining_time":0.9328625495},
{"learn":[19.62499435],"iteration":182,"passed_time":0.2085969373,"remaining_time":0.9312770371},
{"learn":[19.57527079],"iteration":183,"passed_time":0.2100868321,"remaining_time":0.9316894294},
{"learn":[19.53119876],"iteration":184,"passed_time":0.2111393878,"remaining_time":0.9301546001},
{"learn":[19.45081062],"iteration":185,"passed_time":0.2121573179,"remaining_time":0.9284734237},
{"learn":[19.40238935],"iteration":186,"passed_time":0.2131699147,"remaining_time":0.9267761533},
{"learn":[19.34993245],"iteration":187,"passed_time":0.2139515084,"remaining_time":0.9240884301},
{"learn":[19.30714132],"iteration":188,"passed_time":0.2147306438,"remaining_time":0.9214103286},
{"learn":[19.23886614],"iteration":189,"passed_time":0.2154495283,"remaining_time":0.9184953577},
{"learn":[19.17362112],"iteration":190,"passed_time":0.2161382458,"remaining_time":0.9154756066},
{"learn":[19.08211427],"iteration":191,"passed_time":0.2174555967,"remaining_time":0.9151256359},
{"learn":[19.03721674],"iteration":192,"passed_time":0.2187249052,"remaining_time":0.9145647589},
{"learn":[18.99899662],"iteration":193,"passed_time":0.2198524202,"remaining_time":0.9134074775},
{"learn":[18.91758228],"iteration":194,"passed_time":0.2211115619,"remaining_time":0.9127938836},
{"learn":[18.87529638],"iteration":195,"passed_time":0.2218954056,"remaining_time":0.9102240108},
{"learn":[18.80548954],"iteration":196,"passed_time":0.2228816271,"remaining_time":0.9084971905},
{"learn":[18.75184617],"iteration":197,"passed_time":0.2242437285,"remaining_time":0.9083003547},
{"learn":[18.70016138],"iteration":198,"passed_time":0.2252537419,"remaining_time":0.9066746093},
{"learn":[18.66562997],"iteration":199,"passed_time":0.2261016698,"remaining_time":0.9044066793},
{"learn":[18.61895054],"iteration":200,"passed_time":0.226790804,"remaining_time":0.9015216536},
{"learn":[18.5919616],"iteration":201,"passed_time":0.2277116912,"remaining_time":0.8995739088},
{"learn":[18.53439297],"iteration":202,"passed_time":0.2287440799,"remaining_time":0.8980740478},
{"learn":[18.4869464],"iteration":203,"passed_time":0.2297316347,"remaining_time":0.8964038295},
{"learn":[18.45753765],"iteration":204,"passed_time":0.2305171451,"remaining_time":0.8939567336},
{"learn":[18.37457302],"iteration":205,"passed_time":0.2312636134,"remaining_time":0.8913752865},
{"learn":[18.28569334],"iteration":206,"passed_time":0.2319672894,"remaining_time":0.8886476352},
{"learn":[18.23169875],"iteration":207,"passed_time":0.232661757,"remaining_time":0.8859043823},
{"learn":[18.18574287],"iteration":208,"passed_time":0.2339280654,"remaining_time":0.885344975},
{"learn":[18.12480488],"iteration":209,"passed_time":0.2349465373,"remaining_time":0.8838464975},
{"learn":[18.03054815],"iteration":210,"passed_time":0.2360289267,"remaining_time":0.8825915789},
{"learn":[17.99074322],"iteration":211,"passed_time":0.2373235272,"remaining_time":0.8821270728},
{"learn":[17.95113099],"iteration":212,"passed_time":0.2383494575,"remaining_time":0.8806620801},
{"learn":[17.9071373],"iteration":213,"passed_time":0.2392322609,"remaining_time":0.8786755003},
{"learn":[17.86685171],"iteration":214,"passed_time":0.2399028531,"remaining_time":0.8759243707},
{"learn":[17.83701031],"iteration":215,"passed_time":0.2406137376,"remaining_time":0.8733387512},
{"learn":[17.80618475],"iteration":216,"passed_time":0.2413132885,"remaining_time":0.8707295158},
{"learn":[17.75881882],"iteration":217,"passed_time":0.2420120478,"remaining_time":0.8681349605},
{"learn":[17.7009034],"iteration":218,"passed_time":0.2427685162,"remaining_time":0.8657635212},
{"learn":[17.66613266],"iteration":219,"passed_time":0.2437532793,"remaining_time":0.864216172},
{"learn":[17.61300111],"iteration":220,"passed_time":0.2447077086,"remaining_time":0.862566991},
{"learn":[17.55562563],"iteration":221,"passed_time":0.2456607213,"remaining_time":0.8609191043},
{"learn":[17.49553697],"iteration":222,"passed_time":0.2465081075,"remaining_time":0.858909415},
{"learn":[17.45841235],"iteration":223,"passed_time":0.2472882846,"remaining_time":0.8566772715},
{"learn":[17.3958397],"iteration":224,"passed_time":0.2480889619,"remaining_time":0.8545286464},
{"learn":[17.35925502],"iteration":225,"passed_time":0.2491338091,"remaining_time":0.853228178},
{"learn":[17.32147691],"iteration":226,"passed_time":0.249953945,"remaining_time":0.8511647553},
{"learn":[17.28837576],"iteration":227,"passed_time":0.2514512982,"remaining_time":0.8514052728},
{"learn":[17.23725959],"iteration":228,"passed_time":0.2522566839,"remaining_time":0.8493008877},
{"learn":[17.21160076],"iteration":229,"passed_time":0.2530181107,"remaining_time":0.8470606314},
{"learn":[17.192172],"iteration":230,"passed_time":0.2538751221,"remaining_time":0.8451513803},
{"learn":[17.1584074],"iteration":231,"passed_time":0.2549791784,"remaining_time":0.8440690043},
{"learn":[17.12013659],"iteration":232,"passed_time":0.2557047297,"remaining_time":0.8417404621},
{"learn":[17.08243424],"iteration":233,"passed_time":0.2569905384,"remaining_time":0.8412596258},
{"learn":[17.02469025],"iteration":234,"passed_time":0.2578299246,"remaining_time":0.8393186907},
{"learn":[17.00356865],"iteration":235,"passed_time":0.2584842249,"remaining_time":0.8367879146},
{"learn":[16.96583776],"iteration":236,"passed_time":0.2591767758,"remaining_time":0.8343961179},
{"learn":[16.92224775],"iteration":237,"passed_time":0.2600805378,"remaining_time":0.8326948311},
{"learn":[16.86746043],"iteration":238,"passed_time":0.2611330518,"remaining_time":0.8314738595},
{"learn":[16.83217431],"iteration":239,"passed_time":0.2619094788,"remaining_time":0.8293800161},
{"learn":[16.8012804],"iteration":240,"passed_time":0.2626609887,"remaining_time":0.8272186326},
{"learn":[16.77760923],"iteration":241,"passed_time":0.2637257529,"remaining_time":0.8260500855},
{"learn":[16.75545626],"iteration":242,"passed_time":0.2645220968,"remaining_time":0.8240462028},
{"learn":[16.68225743],"iteration":243,"passed_time":0.2653741498,"remaining_time":0.8222248247},
{"learn":[16.65156253],"iteration":244,"passed_time":0.2660604506,"remaining_time":0.8199005722},
{"learn":[16.61860722],"iteration":245,"passed_time":0.2668313775,"remaining_time":0.8178490188},
{"learn":[16.60272915],"iteration":246,"passed_time":0.2675835125,"remaining_time":0.8157505461},
{"learn":[16.57747142],"iteration":247,"passed_time":0.2683468143,"remaining_time":0.8136967917},
{"learn":[16.55462968],"iteration":248,"passed_time":0.2691652835,"remaining_time":0.8118197907},
{"learn":[16.52440838],"iteration":249,"passed_time":0.2698535843,"remaining_time":0.8095607529},
{"learn":[16.49147615],"iteration":250,"passed_time":0.2707445961,"remaining_time":0.8079191334},
{"learn":[16.45926443],"iteration":251,"passed_time":0.2714785642,"remaining_time":0.8058173255},
{"learn":[16.41116221],"iteration":252,"passed_time":0.2722576995,"remaining_time":0.80385969},
{"learn":[16.38237416],"iteration":253,"passed_time":0.2731160026,"remaining_time":0.8021438502},
{"learn":[16.33623675],"iteration":254,"passed_time":0.2738568875,"remaining_time":0.8000916908},
{"learn":[16.29495385],"iteration":255,"passed_time":0.2745945223,"remaining_time":0.7980403303},
{"learn":[16.26455819],"iteration":256,"passed_time":0.2753737409,"remaining_time":0.7961194145},
{"learn":[16.19863402],"iteration":257,"passed_time":0.2762503776,"remaining_time":0.79448752},
{"learn":[16.17272798],"iteration":258,"passed_time":0.2771003889,"remaining_time":0.7927852824},
{"learn":[16.12967212],"iteration":259,"passed_time":0.2777608143,"remaining_time":0.79055001},
{"learn":[16.09793387],"iteration":260,"passed_time":0.2784286982,"remaining_time":0.7883479232},
{"learn":[16.07725047],"iteration":261,"passed_time":0.2791342076,"remaining_time":0.7862635312},
{"learn":[16.05814099],"iteration":262,"passed_time":0.2797829245,"remaining_time":0.7840304766},
{"learn":[16.01957481],"iteration":263,"passed_time":0.2804800588,"remaining_time":0.7819444062},
{"learn":[15.97932776],"iteration":264,"passed_time":0.2811912349,"remaining_time":0.7799077647},
{"learn":[15.91437883],"iteration":265,"passed_time":0.2819895788,"remaining_time":0.7781216197},
{"learn":[15.88102073],"iteration":266,"passed_time":0.2827945062,"remaining_time":0.7763609476},
{"learn":[15.84847397],"iteration":267,"passed_time":0.2835764332,"remaining_time":0.7745445863},
{"learn":[15.82134458],"iteration":268,"passed_time":0.2844963204,"remaining_time":0.7731108187},
{"learn":[15.77666868],"iteration":269,"passed_time":0.2857376286,"remaining_time":0.7725498847},
{"learn":[15.75064331],"iteration":270,"passed_time":0.2872172732,"remaining_time":0.7726250635},
{"learn":[15.72350736],"iteration":271,"passed_time":0.288199828,"remaining_time":0.7713583631},
{"learn":[15.69274205],"iteration":272,"passed_time":0.2889874634,"remaining_time":0.7695746737},
{"learn":[15.65688475],"iteration":273,"passed_time":0.2898830587,"remaining_time":0.7680843087},
{"learn":[15.64198145],"iteration":274,"passed_time":0.2906360687,"remaining_time":0.7662223628},
{"learn":[15.58813645],"iteration":275,"passed_time":0.2915504975,"remaining_time":0.7647918847},
{"learn":[15.52894128],"iteration":276,"passed_time":0.2923348412,"remaining_time":0.7630255964},
{"learn":[15.4756747],"iteration":277,"passed_time":0.2932489784,"remaining_time":0.7616034618},
{"learn":[15.45099481],"iteration":278,"passed_time":0.2941102398,"remaining_time":0.7600483258},
{"learn":[15.41909508],"iteration":279,"passed_time":0.2951476286,"remaining_time":0.7589510449},
{"learn":[15.39189509],"iteration":280,"passed_time":0.2959107637,"remaining_time":0.7571524524},
{"learn":[15.36156251],"iteration":281,"passed_time":0.2969457775,"remaining_time":0.7560534334},
{"learn":[15.32131969],"iteration":282,"passed_time":0.2977588716,"remaining_time":0.7543926181},
{"learn":[15.27383191],"iteration":283,"passed_time":0.2984362556,"remaining_time":0.7523956303},
{"learn":[15.24332071],"iteration":284,"passed_time":0.2991735571,"remaining_time":0.7505582221},
{"learn":[15.17937256],"iteration":285,"passed_time":0.2998818165,"remaining_time":0.7486560033},
{"learn":[15.14045179],"iteration":286,"passed_time":0.3005834924,"remaining_time":0.7467457495},
{"learn":[15.11058312],"iteration":287,"passed_time":0.3012155008,"remaining_time":0.7446716549},
{"learn":[15.0781259],"iteration":288,"passed_time":0.3019048017,"remaining_time":0.7427484913},
{"learn":[15.05147461],"iteration":289,"passed_time":0.302611311,"remaining_time":0.7408759684},
{"learn":[15.0237559],"iteration":290,"passed_time":0.3034490305,"remaining_time":0.7393311431},
{"learn":[14.99150781],"iteration":291,"passed_time":0.3045054612,"remaining_time":0.7383214607},
{"learn":[14.96605405],"iteration":292,"passed_time":0.3056637266,"remaining_time":0.7375571833},
{"learn":[14.93868984],"iteration":293,"passed_time":0.3066460313,"remaining_time":0.7363676806},
{"learn":[14.90247718],"iteration":294,"passed_time":0.3074819174,"remaining_time":0.734829667},
{"learn":[14.85732722],"iteration":295,"passed_time":0.3083915962,"remaining_time":0.7334719044},
{"learn":[14.82206907],"iteration":296,"passed_time":0.3092211905,"remaining_time":0.7319275991},
{"learn":[14.77632446],"iteration":297,"passed_time":0.3100059509,"remaining_time":0.730282475},
{"learn":[14.75795729],"iteration":298,"passed_time":0.310712252,"remaining_time":0.7284591593},
{"learn":[14.7339361],"iteration":299,"passed_time":0.3114238864,"remaining_time":0.726655735},
{"learn":[14.7034789],"iteration":300,"passed_time":0.3120893536,"remaining_time":0.7247523527},
{"learn":[14.68265085],"iteration":301,"passed_time":0.3127392372,"remaining_time":0.722821151},
{"learn":[14.66061739],"iteration":302,"passed_time":0.3136100821,"remaining_time":0.7214066906},
{"learn":[14.63143393],"iteration":303,"passed_time":0.3143576337,"remaining_time":0.7197135299},
{"learn":[14.57951095],"iteration":304,"passed_time":0.315106977,"remaining_time":0.7180306526},
{"learn":[14.54957211],"iteration":305,"passed_time":0.3158583203,"remaining_time":0.7163584128},
{"learn":[14.52723963],"iteration":306,"passed_time":0.316634664,"remaining_time":0.7147486063},
{"learn":[14.50366799],"iteration":307,"passed_time":0.3173515068,"remaining_time":0.7130105283},
{"learn":[14.4674657],"iteration":308,"passed_time":0.3180310575,"remaining_time":0.7111956659},
{"learn":[14.44609877],"iteration":309,"passed_time":0.3188241097,"remaining_time":0.7096407604},
{"learn":[14.42193743],"iteration":310,"passed_time":0.319623162,"remaining_time":0.708104047},
{"learn":[14.37190565],"iteration":311,"passed_time":0.3203796304,"remaining_time":0.7064781593},
{"learn":[14.3419881],"iteration":312,"passed_time":0.3211194319,"remaining_time":0.7048212451},
{"learn":[14.31906746],"iteration":313,"passed_time":0.3217889824,"remaining_time":0.7030166941},
{"learn":[14.30360469],"iteration":314,"passed_time":0.3224964502,"remaining_time":0.7013018043},
{"learn":[14.28278742],"iteration":315,"passed_time":0.3231783759,"remaining_time":0.6995380035},
{"learn":[14.24979558],"iteration":316,"passed_time":0.3238785935,"remaining_time":0.6978204397},
{"learn":[14.22973134],"iteration":317,"passed_time":0.3245837696,"remaining_time":0.6961199083},
{"learn":[14.19849434],"iteration":318,"passed_time":0.3255877829,"remaining_time":0.6950635741},
{"learn":[14.16325733],"iteration":319,"passed_time":0.3264137105,"remaining_time":0.6936291349},
{"learn":[14.12580007],"iteration":320,"passed_time":0.3271404285,"remaining_time":0.6919886323},
{"learn":[14.1023091],"iteration":321,"passed_time":0.327953856,"remaining_time":0.69053638},
{"learn":[14.06623797],"iteration":322,"passed_time":0.328708866,"remaining_time":0.6889656418},
{"learn":[14.05252517],"iteration":323,"passed_time":0.3293937501,"remaining_time":0.6872536268},
{"learn":[14.03612167],"iteration":324,"passed_time":0.3302898454,"remaining_time":0.6859866019},
{"learn":[14.0248774],"iteration":325,"passed_time":0.3310821475,"remaining_time":0.6845072621},
{"learn":[13.99656179],"iteration":326,"passed_time":0.3318211157,"remaining_time":0.6829223574},
{"learn":[13.97588337],"iteration":327,"passed_time":0.3326314598,"remaining_time":0.6814888444},
{"learn":[13.95725702],"iteration":328,"passed_time":0.3334686792,"remaining_time":0.6801139324},
{"learn":[13.91490055],"iteration":329,"passed_time":0.3344905261,"remaining_time":0.6791171288},
{"learn":[13.88644964],"iteration":330,"passed_time":0.3352412028,"remaining_time":0.6775720987},
{"learn":[13.85608267],"iteration":331,"passed_time":0.3362145074,"remaining_time":0.676479792},
{"learn":[13.84176836],"iteration":332,"passed_time":0.336960934,"remaining_time":0.6749337626},
{"learn":[13.7997301],"iteration":333,"passed_time":0.3376674017,"remaining_time":0.6733128429},
{"learn":[13.76808246],"iteration":334,"passed_time":0.3383892863,"remaining_time":0.6717279862},
{"learn":[13.74782819],"iteration":335,"passed_time":0.3390682536,"remaining_time":0.6700634536},
{"learn":[13.70978716],"iteration":336,"passed_time":0.3398852228,"remaining_time":0.6686762692},
{"learn":[13.68972919],"iteration":337,"passed_time":0.3407704012,"remaining_time":0.6674260521},
{"learn":[13.67091833],"iteration":338,"passed_time":0.3414926192,"remaining_time":0.6658602397},
{"learn":[13.64546708],"iteration":339,"passed_time":0.3422171704,"remaining_time":0.6643039191},
{"learn":[13.62508471],"iteration":340,"passed_time":0.3430480981,"remaining_time":0.6629580548},
{"learn":[13.61470873],"iteration":341,"passed_time":0.3437749411,"remaining_time":0.6614149452},
{"learn":[13.59631854],"iteration":342,"passed_time":0.3445812018,"remaining_time":0.6600287161},
{"learn":[13.58285593],"iteration":343,"passed_time":0.3453208367,"remaining_time":0.6585188048},
{"learn":[13.55203605],"iteration":344,"passed_time":0.3460636799,"remaining_time":0.6570194502},
{"learn":[13.53402976],"iteration":345,"passed_time":0.3467553974,"remaining_time":0.6554278321},
{"learn":[13.50413368],"iteration":346,"passed_time":0.3474219479,"remaining_time":0.6537940403},
{"learn":[13.47685316],"iteration":347,"passed_time":0.3480692898,"remaining_time":0.6521298189},
{"learn":[13.46314035],"iteration":348,"passed_time":0.3488070496,"remaining_time":0.650640084},
{"learn":[13.4471128],"iteration":349,"passed_time":0.349515559,"remaining_time":0.6491003239},
{"learn":[13.40535741],"iteration":350,"passed_time":0.3501874013,"remaining_time":0.6474975027},
{"learn":[13.37690371],"iteration":351,"passed_time":0.3509136193,"remaining_time":0.6460000719},
{"learn":[13.35186313],"iteration":352,"passed_time":0.3516113369,"remaining_time":0.6444547733},
{"learn":[13.34005986],"iteration":353,"passed_time":0.3523155962,"remaining_time":0.642926201},
{"learn":[13.29935289],"iteration":354,"passed_time":0.3530065637,"remaining_time":0.6413781229},
{"learn":[13.27544438],"iteration":355,"passed_time":0.3536964062,"remaining_time":0.6398328248},
{"learn":[13.23687136],"iteration":356,"passed_time":0.3543707069,"remaining_time":0.6382643264},
{"learn":[13.21979274],"iteration":357,"passed_time":0.3550401741,"remaining_time":0.6366921558},
{"learn":[13.19020344],"iteration":358,"passed_time":0.3557753922,"remaining_time":0.6352424134},
{"learn":[13.15964364],"iteration":359,"passed_time":0.356539194,"remaining_time":0.633847456},
{"learn":[13.13125915],"iteration":360,"passed_time":0.3573250794,"remaining_time":0.6324950852},
{"learn":[13.10672971],"iteration":361,"passed_time":0.3580368806,"remaining_time":0.6310152757},
{"learn":[13.08856358],"iteration":362,"passed_time":0.358920684,"remaining_time":0.6298415308},
{"learn":[13.06116984],"iteration":363,"passed_time":0.3598564881,"remaining_time":0.6287602374},
{"learn":[13.04353831],"iteration":364,"passed_time":0.3605703725,"remaining_time":0.6272936618},
{"learn":[13.0099346],"iteration":365,"passed_time":0.3612782153,"remaining_time":0.6258207336},
{"learn":[12.98907832],"iteration":366,"passed_time":0.3619685995,"remaining_time":0.6243218623},
{"learn":[12.97514979],"iteration":367,"passed_time":0.3626501502,"remaining_time":0.6228122144},
{"learn":[12.95911671],"iteration":368,"passed_time":0.3633726598,"remaining_time":0.6213770957},
{"learn":[12.9260927],"iteration":369,"passed_time":0.3640404186,"remaining_time":0.6198526047},
{"learn":[12.91313646],"iteration":370,"passed_time":0.364671052,"remaining_time":0.618269789},
{"learn":[12.8831605],"iteration":371,"passed_time":0.3653432276,"remaining_time":0.616762223},
{"learn":[12.85891109],"iteration":372,"passed_time":0.3660000697,"remaining_time":0.6152333611},
{"learn":[12.82404209],"iteration":373,"passed_time":0.3666190362,"remaining_time":0.6136457665},
{"learn":[12.81380283],"iteration":374,"passed_time":0.3673401291,"remaining_time":0.6122335486},
{"learn":[12.79754837],"iteration":375,"passed_time":0.3679695125,"remaining_time":0.610672808},
{"learn":[12.77109086],"iteration":376,"passed_time":0.3685854373,"remaining_time":0.6090947678},
{"learn":[12.74873487],"iteration":377,"passed_time":0.3692559462,"remaining_time":0.6076116364},
{"learn":[12.73000953],"iteration":378,"passed_time":0.3699247468,"remaining_time":0.6061299941},
{"learn":[12.70811083],"iteration":379,"passed_time":0.3706199227,"remaining_time":0.6046956633},
{"learn":[12.68200637],"iteration":380,"passed_time":0.3713361405,"remaining_time":0.6032993989},
{"learn":[12.65952488],"iteration":381,"passed_time":0.3720594835,"remaining_time":0.601918222},
{"learn":[12.64155756],"iteration":382,"passed_time":0.3727894515,"remaining_time":0.600551153},
{"learn":[12.61640668],"iteration":383,"passed_time":0.3737658395,"remaining_time":0.5995827008},
{"learn":[12.59309176],"iteration":384,"passed_time":0.3747582693,"remaining_time":0.5986398328},
{"learn":[12.57864145],"iteration":385,"passed_time":0.3756490312,"remaining_time":0.5975349874},
{"learn":[12.55119295],"iteration":386,"passed_time":0.3763845409,"remaining_time":0.5961853323},
{"learn":[12.53846957],"iteration":387,"passed_time":0.3770552998,"remaining_time":0.5947367101},
{"learn":[12.51857704],"iteration":388,"passed_time":0.3778245601,"remaining_time":0.5934468026},
{"learn":[12.49839696],"iteration":389,"passed_time":0.378576195,"remaining_time":0.5921319974},
{"learn":[12.48395092],"iteration":390,"passed_time":0.3792509957,"remaining_time":0.5907003999},
{"learn":[12.45377896],"iteration":391,"passed_time":0.3800640898,"remaining_time":0.5894871597},
{"learn":[12.42749698],"iteration":392,"passed_time":0.3812553973,"remaining_time":0.5888601174},
{"learn":[12.41202542],"iteration":393,"passed_time":0.3821719095,"remaining_time":0.5878075562},
{"learn":[12.38351783],"iteration":394,"passed_time":0.3832964661,"remaining_time":0.5870743341},
{"learn":[12.36605703],"iteration":395,"passed_time":0.384467315,"remaining_time":0.586409743},
{"learn":[12.35435866],"iteration":396,"passed_time":0.3856511223,"remaining_time":0.5857622841},
{"learn":[12.33218845],"iteration":397,"passed_time":0.3865551344,"remaining_time":0.5846889218},
{"learn":[12.31332585],"iteration":398,"passed_time":0.38723056,"remaining_time":0.5832720966},
{"learn":[12.30107781],"iteration":399,"passed_time":0.3880139871,"remaining_time":0.5820209806},
{"learn":[12.28956576],"iteration":400,"passed_time":0.388815206,"remaining_time":0.5807987741},
{"learn":[12.26055549],"iteration":401,"passed_time":0.3895252155,"remaining_time":0.5794429822},
{"learn":[12.25055656],"iteration":402,"passed_time":0.3908521081,"remaining_time":0.5790042395},
{"learn":[12.23669918],"iteration":403,"passed_time":0.3917407866,"remaining_time":0.5779146257},
{"learn":[12.23028327],"iteration":404,"passed_time":0.3927847588,"remaining_time":0.5770541518},
{"learn":[12.19663461],"iteration":405,"passed_time":0.3935936028,"remaining_time":0.5758487687},
{"learn":[12.17732136],"iteration":406,"passed_time":0.3943611964,"remaining_time":0.5745852321},
{"learn":[12.15972832],"iteration":407,"passed_time":0.3951239565,"remaining_time":0.5733171134},
{"learn":[12.13725167],"iteration":408,"passed_time":0.3958582579,"remaining_time":0.5720103434},
{"learn":[12.12368455],"iteration":409,"passed_time":0.3965821842,"remaining_time":0.5706914358},
{"learn":[12.09291279],"iteration":410,"passed_time":0.3972689017,"remaining_time":0.5693220999},
{"learn":[12.07429214],"iteration":411,"passed_time":0.3979601192,"remaining_time":0.5679625002},
{"learn":[12.06069584],"iteration":412,"passed_time":0.3986489617,"remaining_time":0.5666027615},
{"learn":[12.04027716],"iteration":413,"passed_time":0.3993090954,"remaining_time":0.5652056278},
{"learn":[12.00884509],"iteration":414,"passed_time":0.4000352301,"remaining_time":0.5639050833},
{"learn":[11.97756495],"iteration":415,"passed_time":0.4007486562,"remaining_time":0.5625894597},
{"learn":[11.96382929],"iteration":416,"passed_time":0.4014313736,"remaining_time":0.5612337909},
{"learn":[11.94247576],"iteration":417,"passed_time":0.4020680487,"remaining_time":0.5598172353},
{"learn":[11.92751131],"iteration":418,"passed_time":0.4027516411,"remaining_time":0.5584694594},
{"learn":[11.90752015],"iteration":419,"passed_time":0.4034218167,"remaining_time":0.5571063183},
{"learn":[11.87640791],"iteration":420,"passed_time":0.4041029924,"remaining_time":0.5557615977},
{"learn":[11.86413269],"iteration":421,"passed_time":0.4047567928,"remaining_time":0.5543825266},
{"learn":[11.85082683],"iteration":422,"passed_time":0.4058135151,"remaining_time":0.553556497},
{"learn":[11.83712207],"iteration":423,"passed_time":0.4065599417,"remaining_time":0.5523078454},
{"learn":[11.81494279],"iteration":424,"passed_time":0.407784208,"remaining_time":0.5517080461},
{"learn":[11.789887],"iteration":425,"passed_time":0.4086180941,"remaining_time":0.5505793098},
{"learn":[11.7732914],"iteration":426,"passed_time":0.4093761041,"remaining_time":0.5493501351},
{"learn":[11.73513628],"iteration":427,"passed_time":0.4101635729,"remaining_time":0.548162532},
{"learn":[11.71496408],"iteration":428,"passed_time":0.4109137912,"remaining_time":0.546927214},
{"learn":[11.69311867],"iteration":429,"passed_time":0.411602842,"remaining_time":0.5456130697},
{"learn":[11.67636092],"iteration":430,"passed_time":0.4123861858,"remaining_time":0.5444263102},
{"learn":[11.66447607],"iteration":431,"passed_time":0.4136993699,"remaining_time":0.5439380604},
{"learn":[11.65206666],"iteration":432,"passed_time":0.4145456311,"remaining_time":0.5428345793},
{"learn":[11.63063591],"iteration":433,"passed_time":0.4159249828,"remaining_time":0.5424275121},
{"learn":[11.60844796],"iteration":434,"passed_time":0.4171161236,"remaining_time":0.5417715169},
{"learn":[11.60025688],"iteration":435,"passed_time":0.4179700099,"remaining_time":0.5406768019},
{"learn":[11.57607593],"iteration":436,"passed_time":0.4187225616,"remaining_time":0.5394526366},
{"learn":[11.5581542],"iteration":437,"passed_time":0.4203713752,"remaining_time":0.5393806229},
{"learn":[11.53523995],"iteration":438,"passed_time":0.421590808,"remaining_time":0.5387527182},
{"learn":[11.50722526],"iteration":439,"passed_time":0.4226933644,"remaining_time":0.5379733728},
{"learn":[11.49054866],"iteration":440,"passed_time":0.4240272154,"remaining_time":0.5374857447},
{"learn":[11.48292884],"iteration":441,"passed_time":0.4249781447,"remaining_time":0.5365108705},
{"learn":[11.4642743],"iteration":442,"passed_time":0.425825531,"remaining_time":0.5354059159},
{"learn":[11.44322745],"iteration":443,"passed_time":0.4266338334,"remaining_time":0.5342531787},
{"learn":[11.42602741],"iteration":444,"passed_time":0.4273157591,"remaining_time":0.5329443737},
{"learn":[11.40564347],"iteration":445,"passed_time":0.4280216851,"remaining_time":0.5316681918},
{"learn":[11.39505593],"iteration":446,"passed_time":0.4288029872,"remaining_time":0.5304878119},
{"learn":[11.38017074],"iteration":447,"passed_time":0.4296334982,"remaining_time":0.529369846},
{"learn":[11.36918738],"iteration":448,"passed_time":0.4302939653,"remaining_time":0.5280444875},
{"learn":[11.36123519],"iteration":449,"passed_time":0.4309695576,"remaining_time":0.5267405704},
{"learn":[11.34633533],"iteration":450,"passed_time":0.4332462129,"remaining_time":0.5273884054},
{"learn":[11.33425452],"iteration":451,"passed_time":0.4340371817,"remaining_time":0.5262220698},
{"learn":[11.31321029],"iteration":452,"passed_time":0.4347448578,"remaining_time":0.524956815},
{"learn":[11.30159555],"iteration":453,"passed_time":0.4356168277,"remaining_time":0.5238916033},
{"learn":[11.29074683],"iteration":454,"passed_time":0.4367126339,"remaining_time":0.5230953527},
{"learn":[11.27654315],"iteration":455,"passed_time":0.4380367765,"remaining_time":0.5225701895},
{"learn":[11.264724],"iteration":456,"passed_time":0.4398323003,"remaining_time":0.5226016172},
{"learn":[11.25045675],"iteration":457,"passed_time":0.4408038966,"remaining_time":0.5216500261},
{"learn":[11.23252637],"iteration":458,"passed_time":0.4416624496,"remaining_time":0.5205651095},
{"learn":[11.20781507],"iteration":459,"passed_time":0.4425057108,"remaining_time":0.5194632258},
{"learn":[11.19669969],"iteration":460,"passed_time":0.4433402219,"remaining_time":0.5183522334},
{"learn":[11.17461489],"iteration":461,"passed_time":0.4441794831,"remaining_time":0.5172479695},
{"learn":[11.1648088],"iteration":462,"passed_time":0.4449935356,"remaining_time":0.5161156125},
{"learn":[11.15630533],"iteration":463,"passed_time":0.4458616721,"remaining_time":0.515047104},
{"learn":[11.13775853],"iteration":464,"passed_time":0.446735517,"remaining_time":0.513986025},
{"learn":[11.12157317],"iteration":465,"passed_time":0.4476329873,"remaining_time":0.5129528223},
{"learn":[11.1066796],"iteration":466,"passed_time":0.4484211227,"remaining_time":0.5117954142},
{"learn":[11.09048489],"iteration":467,"passed_time":0.4492524255,"remaining_time":0.5106886546},
{"learn":[11.07772276],"iteration":468,"passed_time":0.4501831461,"remaining_time":0.5096956303},
{"learn":[11.05684833],"iteration":469,"passed_time":0.4510364908,"remaining_time":0.5086156173},
{"learn":[11.04034572],"iteration":470,"passed_time":0.4519976286,"remaining_time":0.5076576338},
{"learn":[11.02732581],"iteration":471,"passed_time":0.4530281423,"remaining_time":0.5067772439},
{"learn":[11.00872516],"iteration":472,"passed_time":0.4538926538,"remaining_time":0.5057112654},
{"learn":[10.98270836],"iteration":473,"passed_time":0.4546974561,"remaining_time":0.5045798775},
{"learn":[10.96132233],"iteration":474,"passed_time":0.4555358839,"remaining_time":0.5034870296},
{"learn":[10.95502035],"iteration":475,"passed_time":0.4563061858,"remaining_time":0.502320255},
{"learn":[10.94145005],"iteration":476,"passed_time":0.4571382802,"remaining_time":0.5012228942},
{"learn":[10.92328663],"iteration":477,"passed_time":0.4578291644,"remaining_time":0.4999724347},
{"learn":[10.9076083],"iteration":478,"passed_time":0.458530132,"remaining_time":0.4987352793},
{"learn":[10.89091666],"iteration":479,"passed_time":0.4593501012,"remaining_time":0.4976292763},
{"learn":[10.87492728],"iteration":480,"passed_time":0.4605509505,"remaining_time":0.4969354331},
{"learn":[10.86299659],"iteration":481,"passed_time":0.4621088462,"remaining_time":0.4966231999},
{"learn":[10.846184],"iteration":482,"passed_time":0.4628853982,"remaining_time":0.4954694635},
{"learn":[10.83073447],"iteration":483,"passed_time":0.4636082411,"remaining_time":0.4942600257},
{"learn":[10.80956492],"iteration":484,"passed_time":0.4643429592,"remaining_time":0.4930652041},
{"learn":[10.78959532],"iteration":485,"passed_time":0.4651280947,"remaining_time":0.491925598},
{"learn":[10.77990026],"iteration":486,"passed_time":0.4659356054,"remaining_time":0.4908110176},
{"learn":[10.76377579],"iteration":487,"passed_time":0.4666448231,"remaining_time":0.4895945685},
{"learn":[10.74835557],"iteration":488,"passed_time":0.467412375,"remaining_time":0.4884411526},
{"learn":[10.73985071],"iteration":489,"passed_time":0.4681470931,"remaining_time":0.4872551377},
{"learn":[10.71456899],"iteration":490,"passed_time":0.4688262271,"remaining_time":0.4860133393},
{"learn":[10.69953054],"iteration":491,"passed_time":0.4694844025,"remaining_time":0.484752188},
{"learn":[10.68783249],"iteration":492,"passed_time":0.4701398696,"remaining_time":0.4834906975},
{"learn":[10.67379708],"iteration":493,"passed_time":0.4707950866,"remaining_time":0.4822314045},
{"learn":[10.66049366],"iteration":494,"passed_time":0.4714865958,"remaining_time":0.4810115775},
{"learn":[10.64080574],"iteration":495,"passed_time":0.4727974049,"remaining_time":0.4804231694},
{"learn":[10.62552791],"iteration":496,"passed_time":0.4738910444,"remaining_time":0.479612063},
{"learn":[10.61387494],"iteration":497,"passed_time":0.4746447211,"remaining_time":0.4784571285},
{"learn":[10.60521771],"iteration":498,"passed_time":0.4753908976,"remaining_time":0.477296272},
{"learn":[10.59187228],"iteration":499,"passed_time":0.4760922403,"remaining_time":0.4760922403},
{"learn":[10.5825448],"iteration":500,"passed_time":0.4767222903,"remaining_time":0.4748192073},
{"learn":[10.56533713],"iteration":501,"passed_time":0.4774140078,"remaining_time":0.4736099122},
{"learn":[10.54495919],"iteration":502,"passed_time":0.4781501843,"remaining_time":0.4724466036},
{"learn":[10.52525537],"iteration":503,"passed_time":0.4788493186,"remaining_time":0.4712485357},
{"learn":[10.51108947],"iteration":504,"passed_time":0.4796113704,"remaining_time":0.4701141155},
{"learn":[10.49929026],"iteration":505,"passed_time":0.4804541315,"remaining_time":0.4690599624},
{"learn":[10.48852021],"iteration":506,"passed_time":0.4811983914,"remaining_time":0.4679108619},
{"learn":[10.47110345],"iteration":507,"passed_time":0.4820620696,"remaining_time":0.4668790123},
{"learn":[10.46119867],"iteration":508,"passed_time":0.4827827041,"remaining_time":0.4657098384},
{"learn":[10.43967637],"iteration":509,"passed_time":0.4834638382,"remaining_time":0.464504472},
{"learn":[10.42415975],"iteration":510,"passed_time":0.4841164302,"remaining_time":0.4632738442},
{"learn":[10.41212128],"iteration":511,"passed_time":0.4848018976,"remaining_time":0.4620768087},
{"learn":[10.40592773],"iteration":512,"passed_time":0.4855054486,"remaining_time":0.4608989347},
{"learn":[10.39310119],"iteration":513,"passed_time":0.486232375,"remaining_time":0.4597450082},
{"learn":[10.37713294],"iteration":514,"passed_time":0.4871831793,"remaining_time":0.4588035766},
{"learn":[10.36372398],"iteration":515,"passed_time":0.4884664046,"remaining_time":0.4581739144},
{"learn":[10.35350754],"iteration":516,"passed_time":0.4893907086,"remaining_time":0.4572064067},
{"learn":[10.33387542],"iteration":517,"passed_time":0.4901755523,"remaining_time":0.4561092977},
{"learn":[10.32321742],"iteration":518,"passed_time":0.4910483973,"remaining_time":0.4550949501},
{"learn":[10.30589997],"iteration":519,"passed_time":0.4918528663,"remaining_time":0.4540180304},
{"learn":[10.29233353],"iteration":520,"passed_time":0.4925978345,"remaining_time":0.4528874525},
{"learn":[10.28065307],"iteration":521,"passed_time":0.493313094,"remaining_time":0.4517311474},
{"learn":[10.27112002],"iteration":522,"passed_time":0.4940473121,"remaining_time":0.45059382},
{"learn":[10.25731279],"iteration":523,"passed_time":0.4947505714,"remaining_time":0.4494299084},
{"learn":[10.24786524],"iteration":524,"passed_time":0.49552204,"remaining_time":0.4483294648},
{"learn":[10.24252081],"iteration":525,"passed_time":0.4962662582,"remaining_time":0.4472057156},
{"learn":[10.22038825],"iteration":526,"passed_time":0.4974401905,"remaining_time":0.4464690894},
{"learn":[10.19995856],"iteration":527,"passed_time":0.4984465789,"remaining_time":0.4455810326},
{"learn":[10.18797937],"iteration":528,"passed_time":0.4991693385,"remaining_time":0.444439997},
{"learn":[10.17783041],"iteration":529,"passed_time":0.4999621407,"remaining_time":0.443362653},
{"learn":[10.16428562],"iteration":530,"passed_time":0.5013685343,"remaining_time":0.4428283288},
{"learn":[10.14412886],"iteration":531,"passed_time":0.5020797105,"remaining_time":0.4416791438},
{"learn":[10.11990109],"iteration":532,"passed_time":0.5028704293,"remaining_time":0.4406012955},
{"learn":[10.10198141],"iteration":533,"passed_time":0.5040822787,"remaining_time":0.439892026},
{"learn":[10.08739803],"iteration":534,"passed_time":0.5051916268,"remaining_time":0.4390917878},
{"learn":[10.07658025],"iteration":535,"passed_time":0.5060187211,"remaining_time":0.4380460571},
{"learn":[10.06745443],"iteration":536,"passed_time":0.5067754812,"remaining_time":0.4369404987},
{"learn":[10.04629812],"iteration":537,"passed_time":0.5074747821,"remaining_time":0.4357868947},
{"learn":[10.03747866],"iteration":538,"passed_time":0.5081387909,"remaining_time":0.4346047915},
{"learn":[10.02323],"iteration":539,"passed_time":0.5087948413,"remaining_time":0.4334178278},
{"learn":[10.00775887],"iteration":540,"passed_time":0.5094752254,"remaining_time":0.4322534722},
{"learn":[9.997497032],"iteration":541,"passed_time":0.5102393605,"remaining_time":0.4311616736},
{"learn":[9.98075293],"iteration":542,"passed_time":0.5109135361,"remaining_time":0.4299953702},
{"learn":[9.967285596],"iteration":543,"passed_time":0.5115745449,"remaining_time":0.4288198391},
{"learn":[9.962157944],"iteration":544,"passed_time":0.512231262,"remaining_time":0.4276426132},
{"learn":[9.940275218],"iteration":545,"passed_time":0.5128862707,"remaining_time":0.4264658734},
{"learn":[9.925575323],"iteration":546,"passed_time":0.5135534879,"remaining_time":0.4253011517},
{"learn":[9.91535036],"iteration":547,"passed_time":0.5142823725,"remaining_time":0.4241891102},
{"learn":[9.893781595],"iteration":548,"passed_time":0.514941673,"remaining_time":0.4230213015},
{"learn":[9.880839309],"iteration":549,"passed_time":0.5157179333,"remaining_time":0.4219510363},
{"learn":[9.875061563],"iteration":550,"passed_time":0.516373067,"remaining_time":0.4207831344},
{"learn":[9.854609252],"iteration":551,"passed_time":0.5170401592,"remaining_time":0.4196267958},
{"learn":[9.83789773],"iteration":552,"passed_time":0.5178013776,"remaining_time":0.4185483107},
{"learn":[9.826045811],"iteration":553,"passed_time":0.5185069703,"remaining_time":0.4174261891},
{"learn":[9.807593376],"iteration":554,"passed_time":0.519311981,"remaining_time":0.4163852821},
{"learn":[9.790685399],"iteration":555,"passed_time":0.5203560365,"remaining_time":0.4155361155},
{"learn":[9.777324236],"iteration":556,"passed_time":0.5218810151,"remaining_time":0.4150687427},
{"learn":[9.760236314],"iteration":557,"passed_time":0.5227258597,"remaining_time":0.4140588351},
{"learn":[9.750388864],"iteration":558,"passed_time":0.5234859948,"remaining_time":0.41298269},
{"learn":[9.737367837],"iteration":559,"passed_time":0.5246458852,"remaining_time":0.4122217669},
{"learn":[9.725304872],"iteration":560,"passed_time":0.5255058966,"remaining_time":0.4112247569},
{"learn":[9.71719284],"iteration":561,"passed_time":0.5261421967,"remaining_time":0.4100538829},
{"learn":[9.695509793],"iteration":562,"passed_time":0.5267537882,"remaining_time":0.408865729},
{"learn":[9.68381297],"iteration":563,"passed_time":0.5274540892,"remaining_time":0.4077481966},
{"learn":[9.672117807],"iteration":564,"passed_time":0.5281095979,"remaining_time":0.406597655},
{"learn":[9.663156789],"iteration":565,"passed_time":0.5287528564,"remaining_time":0.4054394694},
{"learn":[9.656159147],"iteration":566,"passed_time":0.5294071568,"remaining_time":0.4042915324},
{"learn":[9.642397986],"iteration":567,"passed_time":0.5300452069,"remaining_time":0.4031329743},
{"learn":[9.630342256],"iteration":568,"passed_time":0.5306686318,"remaining_time":0.4019651675},
{"learn":[9.62303603],"iteration":569,"passed_time":0.5313787663,"remaining_time":0.4008646833},
{"learn":[9.607459651],"iteration":570,"passed_time":0.5320681921,"remaining_time":0.3997500077},
{"learn":[9.595648305],"iteration":571,"passed_time":0.5327988268,"remaining_time":0.3986676536},
{"learn":[9.584265446],"iteration":572,"passed_time":0.5334982944,"remaining_time":0.3975633014},
{"learn":[9.573409508],"iteration":573,"passed_time":0.5341734284,"remaining_time":0.3964423005},
{"learn":[9.5624882],"iteration":574,"passed_time":0.5348692293,"remaining_time":0.395338126},
{"learn":[9.554112245],"iteration":575,"passed_time":0.5359956609,"remaining_time":0.3945523615},
{"learn":[9.5446268],"iteration":576,"passed_time":0.536855214,"remaining_time":0.393569767},
{"learn":[9.532460027],"iteration":577,"passed_time":0.5376491412,"remaining_time":0.3925396844},
{"learn":[9.507749494],"iteration":578,"passed_time":0.5383597757,"remaining_time":0.3914498542},
{"learn":[9.497962861],"iteration":579,"passed_time":0.5390437014,"remaining_time":0.3903419907},
{"learn":[9.489122773],"iteration":580,"passed_time":0.5397560442,"remaining_time":0.3892560801},
{"learn":[9.475520087],"iteration":581,"passed_time":0.540439845,"remaining_time":0.3881509539},
{"learn":[9.457905867],"iteration":582,"passed_time":0.5411910633,"remaining_time":0.3870954947},
{"learn":[9.442498587],"iteration":583,"passed_time":0.5420794917,"remaining_time":0.386138816},
{"learn":[9.434927472],"iteration":584,"passed_time":0.5431671312,"remaining_time":0.3853236914},
{"learn":[9.426559969],"iteration":585,"passed_time":0.5441942698,"remaining_time":0.3844648937},
{"learn":[9.412705597],"iteration":586,"passed_time":0.5450470728,"remaining_time":0.3834828638},
{"learn":[9.405482299],"iteration":587,"passed_time":0.5462461721,"remaining_time":0.3827439165},
{"learn":[9.39206329],"iteration":588,"passed_time":0.5473253531,"remaining_time":0.3819197286},
{"learn":[9.373532598],"iteration":589,"passed_time":0.5483479917,"remaining_time":0.381055384},
{"learn":[9.367523222],"iteration":590,"passed_time":0.5490946266,"remaining_time":0.3799994962},
{"learn":[9.360313395],"iteration":591,"passed_time":0.5497671772,"remaining_time":0.3788935951},
{"learn":[9.344063455],"iteration":592,"passed_time":0.5505122288,"remaining_time":0.3778389159},
{"learn":[9.334159153],"iteration":593,"passed_time":0.551337448,"remaining_time":0.3768400739},
{"learn":[9.325944792],"iteration":594,"passed_time":0.5524064206,"remaining_time":0.3760077317},
{"learn":[9.309067623],"iteration":595,"passed_time":0.5535833945,"remaining_time":0.3752478044},
{"learn":[9.294098763],"iteration":596,"passed_time":0.5543665716,"remaining_time":0.3742206505},
{"learn":[9.284120958],"iteration":597,"passed_time":0.5550847478,"remaining_time":0.3731506164},
{"learn":[9.272287957],"iteration":598,"passed_time":0.5559677595,"remaining_time":0.3721921061},
{"learn":[9.261651344],"iteration":599,"passed_time":0.5567973956,"remaining_time":0.3711982637},
{"learn":[9.249696538],"iteration":600,"passed_time":0.5577719918,"remaining_time":0.3703012059},
{"learn":[9.237078363],"iteration":601,"passed_time":0.5584422507,"remaining_time":0.369202684},
{"learn":[9.231531194],"iteration":602,"passed_time":0.5591264265,"remaining_time":0.3681147451},
{"learn":[9.219590452],"iteration":603,"passed_time":0.5599374789,"remaining_time":0.3671113273},
{"learn":[9.209232331],"iteration":604,"passed_time":0.5606868639,"remaining_time":0.366068283},
{"learn":[9.199541143],"iteration":605,"passed_time":0.5614137069,"remaining_time":0.365011552},
{"learn":[9.191258405],"iteration":606,"passed_time":0.5621129662,"remaining_time":0.3639380489},
{"learn":[9.183725517],"iteration":607,"passed_time":0.5629242269,"remaining_time":0.3629379884},
{"learn":[9.172885682],"iteration":608,"passed_time":0.5637660715,"remaining_time":0.3619581838},
{"learn":[9.16607153],"iteration":609,"passed_time":0.5645994575,"remaining_time":0.3609734237},
{"learn":[9.158386799],"iteration":610,"passed_time":0.5656096793,"remaining_time":0.3601017434},
{"learn":[9.143119635],"iteration":611,"passed_time":0.5663309805,"remaining_time":0.3590464386},
{"learn":[9.131281014],"iteration":612,"passed_time":0.5670866572,"remaining_time":0.3580139255},
{"learn":[9.124629582],"iteration":613,"passed_time":0.5678418339,"remaining_time":0.3569819998},
{"learn":[9.107792377],"iteration":614,"passed_time":0.5687664712,"remaining_time":0.3560570592},
{"learn":[9.097276006],"iteration":615,"passed_time":0.569952487,"remaining_time":0.3552950568},
{"learn":[9.073123009],"iteration":616,"passed_time":0.570658413,"remaining_time":0.3542336664},
{"learn":[9.063670286],"iteration":617,"passed_time":0.5714250065,"remaining_time":0.3532109264},
{"learn":[9.04848753],"iteration":618,"passed_time":0.5721988085,"remaining_time":0.3521934508},
{"learn":[9.039301143],"iteration":619,"passed_time":0.5729343599,"remaining_time":0.3511533174},
{"learn":[9.032363501],"iteration":620,"passed_time":0.5736920783,"remaining_time":0.3501276935},
{"learn":[9.028002517],"iteration":621,"passed_time":0.5746675079,"remaining_time":0.3492352379},
{"learn":[9.020633373],"iteration":622,"passed_time":0.5759577334,"remaining_time":0.3485330104},
{"learn":[9.008409112],"iteration":623,"passed_time":0.5768362451,"remaining_time":0.3475808143},
{"learn":[9.000942925],"iteration":624,"passed_time":0.5780477612,"remaining_time":0.3468286567},
{"learn":[8.992271382],"iteration":625,"passed_time":0.5788312299,"remaining_time":0.3458192971},
{"learn":[8.978418486],"iteration":626,"passed_time":0.5802147899,"remaining_time":0.3451676502},
{"learn":[8.968194035],"iteration":627,"passed_time":0.5810408009,"remaining_time":0.3441834044},
{"learn":[8.959966654],"iteration":628,"passed_time":0.5817852691,"remaining_time":0.3431515657},
{"learn":[8.951184127],"iteration":629,"passed_time":0.5824454029,"remaining_time":0.3420711096},
{"learn":[8.941508215],"iteration":630,"passed_time":0.5830959949,"remaining_time":0.3409864059},
{"learn":[8.925153006],"iteration":631,"passed_time":0.5838819636,"remaining_time":0.3399819029},
{"learn":[8.915417506],"iteration":632,"passed_time":0.5849507278,"remaining_time":0.3391420492},
{"learn":[8.901116425],"iteration":633,"passed_time":0.5859880333,"remaining_time":0.3382833126},
{"learn":[8.897647317],"iteration":634,"passed_time":0.5870295471,"remaining_time":0.3374264326},
{"learn":[8.885040687],"iteration":635,"passed_time":0.5879450593,"remaining_time":0.3364968578},
{"learn":[8.877959422],"iteration":636,"passed_time":0.5892861188,"remaining_time":0.3358098291},
{"learn":[8.872139319],"iteration":637,"passed_time":0.5901876724,"remaining_time":0.3348713752},
{"learn":[8.862611445],"iteration":638,"passed_time":0.590988433,"remaining_time":0.3338760944},
{"learn":[8.855118273],"iteration":639,"passed_time":0.5916859006,"remaining_time":0.3328233191},
{"learn":[8.850339873],"iteration":640,"passed_time":0.5923745348,"remaining_time":0.3317667051},
{"learn":[8.846026438],"iteration":641,"passed_time":0.5930864192,"remaining_time":0.3307242026},
{"learn":[8.833125934],"iteration":642,"passed_time":0.5938543878,"remaining_time":0.3297138669},
{"learn":[8.819926763],"iteration":643,"passed_time":0.5945741473,"remaining_time":0.3286776342},
{"learn":[8.811401062],"iteration":644,"passed_time":0.5952601148,"remaining_time":0.3276237841},
{"learn":[8.804423068],"iteration":645,"passed_time":0.5959625824,"remaining_time":0.3265801148},
{"learn":[8.798071277],"iteration":646,"passed_time":0.5965857157,"remaining_time":0.3254942158},
{"learn":[8.784601477],"iteration":647,"passed_time":0.5972743499,"remaining_time":0.3244453259},
{"learn":[8.778266067],"iteration":648,"passed_time":0.597960234,"remaining_time":0.3233960587},
{"learn":[8.770373961],"iteration":649,"passed_time":0.5986468264,"remaining_time":0.3223482912},
{"learn":[8.756186378],"iteration":650,"passed_time":0.5993302522,"remaining_time":0.3212999355},
{"learn":[8.745482296],"iteration":651,"passed_time":0.6001254294,"remaining_time":0.3203123458},
{"learn":[8.740286095],"iteration":652,"passed_time":0.6018697442,"remaining_time":0.3198297109},
{"learn":[8.73114672],"iteration":653,"passed_time":0.6029171748,"remaining_time":0.3189745298},
{"learn":[8.72234341],"iteration":654,"passed_time":0.6036360594,"remaining_time":0.3179457107},
{"learn":[8.715461486],"iteration":655,"passed_time":0.6044129863,"remaining_time":0.3169482733},
{"learn":[8.706999853],"iteration":656,"passed_time":0.6052614976,"remaining_time":0.3159888793},
{"learn":[8.700373333],"iteration":657,"passed_time":0.6059787155,"remaining_time":0.3149615816},
{"learn":[8.692499258],"iteration":658,"passed_time":0.6067402673,"remaining_time":0.3139581656},
{"learn":[8.682675281],"iteration":659,"passed_time":0.6077702809,"remaining_time":0.3130937811},
{"learn":[8.665077293],"iteration":660,"passed_time":0.608524916,"remaining_time":0.3120876649},
{"learn":[8.652858672],"iteration":661,"passed_time":0.6093295516,"remaining_time":0.3111078375},
{"learn":[8.644663378],"iteration":662,"passed_time":0.6100628114,"remaining_time":0.3100922586},
{"learn":[8.632344805],"iteration":663,"passed_time":0.6107315286,"remaining_time":0.3090448699},
{"learn":[8.626704785],"iteration":664,"passed_time":0.6114640383,"remaining_time":0.3080307562},
{"learn":[8.615398085],"iteration":665,"passed_time":0.6122516738,"remaining_time":0.3070451337},
{"learn":[8.601400752],"iteration":666,"passed_time":0.612991892,"remaining_time":0.3060364318},
{"learn":[8.586835854],"iteration":667,"passed_time":0.6137009847,"remaining_time":0.3050130643},
{"learn":[8.583627463],"iteration":668,"passed_time":0.6144739533,"remaining_time":0.30402224},
{"learn":[8.576902739],"iteration":669,"passed_time":0.6151927545,"remaining_time":0.3030053866},
{"learn":[8.565590191],"iteration":670,"passed_time":0.6158928472,"remaining_time":0.3019802485},
{"learn":[8.549581157],"iteration":671,"passed_time":0.6166258152,"remaining_time":0.3009721241},
{"learn":[8.530885595],"iteration":672,"passed_time":0.6174527429,"remaining_time":0.3000104709},
{"learn":[8.524193271],"iteration":673,"passed_time":0.6186516755,"remaining_time":0.2992291487},
{"learn":[8.519320591],"iteration":674,"passed_time":0.6194298525,"remaining_time":0.298244003},
{"learn":[8.509631546],"iteration":675,"passed_time":0.620125695,"remaining_time":0.2972200077},
{"learn":[8.501433006],"iteration":676,"passed_time":0.6207492033,"remaining_time":0.2961624707},
{"learn":[8.481442849],"iteration":677,"passed_time":0.6213665032,"remaining_time":0.2951032655},
{"learn":[8.463954252],"iteration":678,"passed_time":0.622029137,"remaining_time":0.2940667938},
{"learn":[8.459518916],"iteration":679,"passed_time":0.6226698538,"remaining_time":0.2930211077},
{"learn":[8.449740186],"iteration":680,"passed_time":0.6233939051,"remaining_time":0.2920156472},
{"learn":[8.446405104],"iteration":681,"passed_time":0.6240493722,"remaining_time":0.2909790328},
{"learn":[8.434775792],"iteration":682,"passed_time":0.6247062976,"remaining_time":0.2899442113},
{"learn":[8.427747142],"iteration":683,"passed_time":0.6254973914,"remaining_time":0.2889724791},
{"learn":[8.423031458],"iteration":684,"passed_time":0.6261369832,"remaining_time":0.2879316054},
{"learn":[8.410969299],"iteration":685,"passed_time":0.6268555344,"remaining_time":0.2869280435},
{"learn":[8.405852653],"iteration":686,"passed_time":0.6275657105,"remaining_time":0.2859214955},
{"learn":[8.396962221],"iteration":687,"passed_time":0.6283878881,"remaining_time":0.2849666004},
{"learn":[8.388914655],"iteration":688,"passed_time":0.6298910331,"remaining_time":0.2843194649},
{"learn":[8.380386613],"iteration":689,"passed_time":0.630635793,"remaining_time":0.2833291244},
{"learn":[8.36854781],"iteration":690,"passed_time":0.6312899683,"remaining_time":0.2822989873},
{"learn":[8.356717243],"iteration":691,"passed_time":0.6319472271,"remaining_time":0.2812713092},
{"learn":[8.351612177],"iteration":692,"passed_time":0.6327286958,"remaining_time":0.2802997253},
{"learn":[8.346487351],"iteration":693,"passed_time":0.6340996723,"remaining_time":0.2795886163},
{"learn":[8.336246086],"iteration":694,"passed_time":0.634978809,"remaining_time":0.2786597651},
{"learn":[8.329214797],"iteration":695,"passed_time":0.6362879097,"remaining_time":0.2779188571},
{"learn":[8.322061705],"iteration":696,"passed_time":0.6372616727,"remaining_time":0.2770305406},
{"learn":[8.310295251],"iteration":697,"passed_time":0.6385293562,"remaining_time":0.2762691484},
{"learn":[8.305631703],"iteration":698,"passed_time":0.6393064081,"remaining_time":0.2752950341},
{"learn":[8.300715337],"iteration":699,"passed_time":0.6401129605,"remaining_time":0.2743341259},
{"learn":[8.294115464],"iteration":700,"passed_time":0.6408647205,"remaining_time":0.2733502873},
{"learn":[8.289848777],"iteration":701,"passed_time":0.6415148541,"remaining_time":0.2723239694},
{"learn":[8.279149703],"iteration":702,"passed_time":0.6421665711,"remaining_time":0.2712993906},
{"learn":[8.270429279],"iteration":703,"passed_time":0.6428258716,"remaining_time":0.2702790596},
{"learn":[8.266790872],"iteration":704,"passed_time":0.6435450894,"remaining_time":0.2692848247},
{"learn":[8.260910717],"iteration":705,"passed_time":0.6441943897,"remaining_time":0.2682622529},
{"learn":[8.25301409],"iteration":706,"passed_time":0.6448801072,"remaining_time":0.2672558294},
{"learn":[8.247737754],"iteration":707,"passed_time":0.6455721997,"remaining_time":0.2662529411},
{"learn":[8.240938952],"iteration":708,"passed_time":0.646245917,"remaining_time":0.2652433876},
{"learn":[8.235841515],"iteration":709,"passed_time":0.6469100925,"remaining_time":0.2642308828},
{"learn":[8.228197419],"iteration":710,"passed_time":0.6475183506,"remaining_time":0.2631966291},
{"learn":[8.211883301],"iteration":711,"passed_time":0.6481774843,"remaining_time":0.262184151},
{"learn":[8.199835325],"iteration":712,"passed_time":0.6490749546,"remaining_time":0.2612686002},
{"learn":[8.194319098],"iteration":713,"passed_time":0.6499010905,"remaining_time":0.2603245265},
{"learn":[8.186975669],"iteration":714,"passed_time":0.6506233085,"remaining_time":0.2593393607},
{"learn":[8.183051272],"iteration":715,"passed_time":0.6513531932,"remaining_time":0.2583579705},
{"learn":[8.179892002],"iteration":716,"passed_time":0.6521970794,"remaining_time":0.2574222782},
{"learn":[8.172995154],"iteration":717,"passed_time":0.652922964,"remaining_time":0.2564404956},
{"learn":[8.165513209],"iteration":718,"passed_time":0.6537217246,"remaining_time":0.2554879063},
{"learn":[8.160506819],"iteration":719,"passed_time":0.6544521093,"remaining_time":0.2545091536},
{"learn":[8.151673043],"iteration":720,"passed_time":0.6551437435,"remaining_time":0.2535160949},
{"learn":[8.143523319],"iteration":721,"passed_time":0.6559482959,"remaining_time":0.2525673494},
{"learn":[8.137476591],"iteration":722,"passed_time":0.6567126393,"remaining_time":0.2516035976},
{"learn":[8.127555605],"iteration":723,"passed_time":0.6575012748,"remaining_time":0.2506496572},
{"learn":[8.119169332],"iteration":724,"passed_time":0.6582512431,"remaining_time":0.249681506},
{"learn":[8.113497136],"iteration":725,"passed_time":0.6592875485,"remaining_time":0.2488220225},
{"learn":[8.110463078],"iteration":726,"passed_time":0.6602357695,"remaining_time":0.2479289753},
{"learn":[8.103263674],"iteration":727,"passed_time":0.6612887418,"remaining_time":0.2470749145},
{"learn":[8.096387113],"iteration":728,"passed_time":0.66215517,"remaining_time":0.2461509617},
{"learn":[8.090417532],"iteration":729,"passed_time":0.6632788099,"remaining_time":0.2453222995},
{"learn":[8.082585062],"iteration":730,"passed_time":0.6639463188,"remaining_time":0.2443249791},
{"learn":[8.07026292],"iteration":731,"passed_time":0.6645909523,"remaining_time":0.2433201847},
{"learn":[8.067197879],"iteration":732,"passed_time":0.6653181286,"remaining_time":0.2423464398},
{"learn":[8.047870866],"iteration":733,"passed_time":0.6661567648,"remaining_time":0.2414137594},
{"learn":[8.043478778],"iteration":734,"passed_time":0.6668333571,"remaining_time":0.2404229111},
{"learn":[8.037847442],"iteration":735,"passed_time":0.6675308664,"remaining_time":0.2394404195},
{"learn":[8.032429001],"iteration":736,"passed_time":0.6683149184,"remaining_time":0.2384895842},
{"learn":[8.025018279],"iteration":737,"passed_time":0.669233139,"remaining_time":0.2375868325},
{"learn":[8.021646769],"iteration":738,"passed_time":0.6704569052,"remaining_time":0.2367919516},
{"learn":[8.013336732],"iteration":739,"passed_time":0.6714841689,"remaining_time":0.2359268701},
{"learn":[8.007895683],"iteration":740,"passed_time":0.6730654399,"remaining_time":0.2352549918},
{"learn":[8.002111468],"iteration":741,"passed_time":0.6738743673,"remaining_time":0.2343121115},
{"learn":[7.994363966],"iteration":742,"passed_time":0.6747110451,"remaining_time":0.2333791906},
{"learn":[7.986406224],"iteration":743,"passed_time":0.6754848053,"remaining_time":0.2324248793},
{"learn":[7.974887079],"iteration":744,"passed_time":0.6764478598,"remaining_time":0.2315358446},
{"learn":[7.966387928],"iteration":745,"passed_time":0.6772569122,"remaining_time":0.2305941765},
{"learn":[7.957116249],"iteration":746,"passed_time":0.678016589,"remaining_time":0.2296361406},
{"learn":[7.947965155],"iteration":747,"passed_time":0.6786897646,"remaining_time":0.2286494929},
{"learn":[7.940607335],"iteration":748,"passed_time":0.6795148172,"remaining_time":0.2277145783},
{"learn":[7.928192981],"iteration":749,"passed_time":0.6801177419,"remaining_time":0.226705914},
{"learn":[7.918210752],"iteration":750,"passed_time":0.680802376,"remaining_time":0.2257254216},
{"learn":[7.907077116],"iteration":751,"passed_time":0.68160447,"remaining_time":0.2247844529},
{"learn":[7.897078126],"iteration":752,"passed_time":0.6824146474,"remaining_time":0.2238465045},
{"learn":[7.891000706],"iteration":753,"passed_time":0.6830317806,"remaining_time":0.2228459125},
{"learn":[7.880200895],"iteration":754,"passed_time":0.6836590389,"remaining_time":0.2218496219},
{"learn":[7.871848389],"iteration":755,"passed_time":0.6842939224,"remaining_time":0.2208567686},
{"learn":[7.863491152],"iteration":756,"passed_time":0.6849307225,"remaining_time":0.2198654763},
{"learn":[7.856408026],"iteration":757,"passed_time":0.6856046064,"remaining_time":0.2188869588},
{"learn":[7.852015051],"iteration":758,"passed_time":0.6862696153,"remaining_time":0.2179064259},
{"learn":[7.846164203],"iteration":759,"passed_time":0.686906332,"remaining_time":0.2169177891},
{"learn":[7.83857594],"iteration":760,"passed_time":0.6875754659,"remaining_time":0.215940258},
{"learn":[7.833997649],"iteration":761,"passed_time":0.6882310996,"remaining_time":0.2149593198},
{"learn":[7.826961883],"iteration":762,"passed_time":0.6889254839,"remaining_time":0.2139912709},
{"learn":[7.822447925],"iteration":763,"passed_time":0.6896492435,"remaining_time":0.2130330124},
{"learn":[7.81676962],"iteration":764,"passed_time":0.6902983354,"remaining_time":0.2120524298},
{"learn":[7.810911912],"iteration":765,"passed_time":0.6909827612,"remaining_time":0.2110835067},
{"learn":[7.801007564],"iteration":766,"passed_time":0.6916145196,"remaining_time":0.210099326},
{"learn":[7.795946531],"iteration":767,"passed_time":0.69227157,"remaining_time":0.2091237034},
{"learn":[7.788763032],"iteration":768,"passed_time":0.6929582458,"remaining_time":0.2081578085},
{"learn":[7.780719397],"iteration":769,"passed_time":0.6939182169,"remaining_time":0.2072742726},
{"learn":[7.774589607],"iteration":770,"passed_time":0.6946495182,"remaining_time":0.2063226196},
{"learn":[7.768649841],"iteration":771,"passed_time":0.6954322786,"remaining_time":0.2053867351},
{"learn":[7.76567389],"iteration":772,"passed_time":0.6960456201,"remaining_time":0.2044014952},
{"learn":[7.75874959],"iteration":773,"passed_time":0.6967387126,"remaining_time":0.2034405027},
{"learn":[7.751009723],"iteration":774,"passed_time":0.6974374719,"remaining_time":0.2024818467},
{"learn":[7.740894869],"iteration":775,"passed_time":0.6982275658,"remaining_time":0.2015502252},
{"learn":[7.737631001],"iteration":776,"passed_time":0.6990351181,"remaining_time":0.2006239786},
{"learn":[7.73123629],"iteration":777,"passed_time":0.6997727113,"remaining_time":0.1996780744},
{"learn":[7.726432647],"iteration":778,"passed_time":0.7005653051,"remaining_time":0.1987483086},
{"learn":[7.715459733],"iteration":779,"passed_time":0.7012111887,"remaining_time":0.1977775148},
{"learn":[7.710400124],"iteration":780,"passed_time":0.7019588236,"remaining_time":0.196836085},
{"learn":[7.705730765],"iteration":781,"passed_time":0.7026917917,"remaining_time":0.1958910621},
{"learn":[7.701071386],"iteration":782,"passed_time":0.7036318875,"remaining_time":0.1950039842},
{"learn":[7.693450199],"iteration":783,"passed_time":0.7043041465,"remaining_time":0.1940429791},
{"learn":[7.683392417],"iteration":784,"passed_time":0.7049476967,"remaining_time":0.1930748469},
{"learn":[7.676864007],"iteration":785,"passed_time":0.7055811634,"remaining_time":0.1921047951},
{"learn":[7.672104077],"iteration":786,"passed_time":0.7061827964,"remaining_time":0.191126983},
{"learn":[7.663078628],"iteration":787,"passed_time":0.7068395135,"remaining_time":0.1901649452},
{"learn":[7.65997907],"iteration":788,"passed_time":0.7075751066,"remaining_time":0.189224775},
{"learn":[7.650509618],"iteration":789,"passed_time":0.7082774076,"remaining_time":0.1882762729},
{"learn":[7.645348554],"iteration":790,"passed_time":0.7089574166,"remaining_time":0.1873225032},
{"learn":[7.636800128],"iteration":791,"passed_time":0.7095816749,"remaining_time":0.1863547833},
{"learn":[7.630364495],"iteration":792,"passed_time":0.7103777271,"remaining_time":0.1854327737},
{"learn":[7.626762007],"iteration":793,"passed_time":0.7111361122,"remaining_time":0.1845013087},
{"learn":[7.619341051],"iteration":794,"passed_time":0.7118300381,"remaining_time":0.1835536576},
{"learn":[7.613032758],"iteration":795,"passed_time":0.7125352141,"remaining_time":0.1826095272},
{"learn":[7.605151534],"iteration":796,"passed_time":0.7132848491,"remaining_time":0.1816773204},
{"learn":[7.601074678],"iteration":797,"passed_time":0.7140389841,"remaining_time":0.1807467103},
{"learn":[7.582531358],"iteration":798,"passed_time":0.7148406197,"remaining_time":0.1798284913},
{"learn":[7.573890145],"iteration":799,"passed_time":0.7157075896,"remaining_time":0.1789268974},
{"learn":[7.564191196],"iteration":800,"passed_time":0.7165533925,"remaining_time":0.1780201312},
{"learn":[7.555522965],"iteration":801,"passed_time":0.7174288208,"remaining_time":0.1771208311},
{"learn":[7.546802601],"iteration":802,"passed_time":0.7181276634,"remaining_time":0.1761782686},
{"learn":[7.533339678],"iteration":803,"passed_time":0.7188910485,"remaining_time":0.1752520467},
{"learn":[7.527088853],"iteration":804,"passed_time":0.7196336001,"remaining_time":0.1743211826},
{"learn":[7.518642217],"iteration":805,"passed_time":0.7203677348,"remaining_time":0.17338876},
{"learn":[7.512308046],"iteration":806,"passed_time":0.7210910361,"remaining_time":0.1724542379},
{"learn":[7.504106304],"iteration":807,"passed_time":0.7220796742,"remaining_time":0.1715832889},
{"learn":[7.499682091],"iteration":808,"passed_time":0.7229642276,"remaining_time":0.1706874753},
{"learn":[7.49095593],"iteration":809,"passed_time":0.7241809938,"remaining_time":0.1698696158},
{"learn":[7.486127079],"iteration":810,"passed_time":0.7258808914,"remaining_time":0.1691633643},
{"learn":[7.481157107],"iteration":811,"passed_time":0.7268148205,"remaining_time":0.168277323},
{"learn":[7.476013156],"iteration":812,"passed_time":0.7275389967,"remaining_time":0.1673429181},
{"learn":[7.46998757],"iteration":813,"passed_time":0.7281402131,"remaining_time":0.1663809332},
{"learn":[7.460859153],"iteration":814,"passed_time":0.7287760548,"remaining_time":0.1654276934},
{"learn":[7.451063943],"iteration":815,"passed_time":0.7295998575,"remaining_time":0.1645176149},
{"learn":[7.448254315],"iteration":816,"passed_time":0.7305705787,"remaining_time":0.1636406559},
{"learn":[7.441945314],"iteration":817,"passed_time":0.7312050871,"remaining_time":0.1626886624},
{"learn":[7.430000756],"iteration":818,"passed_time":0.7320617235,"remaining_time":0.1617865347},
{"learn":[7.426105061],"iteration":819,"passed_time":0.7327613161,"remaining_time":0.160850045},
{"learn":[7.419719817],"iteration":820,"passed_time":0.733582202,"remaining_time":0.1599405775},
{"learn":[7.409083083],"iteration":821,"passed_time":0.7342769196,"remaining_time":0.1590040045},
{"learn":[7.403391146],"iteration":822,"passed_time":0.7349386367,"remaining_time":0.1580609219},
{"learn":[7.40074991],"iteration":823,"passed_time":0.7356627296,"remaining_time":0.1571318452},
{"learn":[7.392464094],"iteration":824,"passed_time":0.7370308728,"remaining_time":0.1563398821},
{"learn":[7.388009024],"iteration":825,"passed_time":0.7382320554,"remaining_time":0.1555113531},
{"learn":[7.380277445],"iteration":826,"passed_time":0.7393605704,"remaining_time":0.1546667215},
{"learn":[7.374682481],"iteration":827,"passed_time":0.7403695422,"remaining_time":0.1537965716},
{"learn":[7.370805137],"iteration":828,"passed_time":0.7412704708,"remaining_time":0.1529038004},
{"learn":[7.361915405],"iteration":829,"passed_time":0.7419520215,"remaining_time":0.1519660767},
{"learn":[7.357287016],"iteration":830,"passed_time":0.7426187387,"remaining_time":0.1510259529},
{"learn":[7.349072224],"iteration":831,"passed_time":0.7432989561,"remaining_time":0.1500892123},
{"learn":[7.342662837],"iteration":832,"passed_time":0.7440042988,"remaining_time":0.1491581247},
{"learn":[7.336490433],"iteration":833,"passed_time":0.7446903079,"remaining_time":0.1482237303},
{"learn":[7.333583164],"iteration":834,"passed_time":0.7454422762,"remaining_time":0.1473029648},
{"learn":[7.330302903],"iteration":835,"passed_time":0.7461724942,"remaining_time":0.1463783362},
{"learn":[7.323117276],"iteration":836,"passed_time":0.7472752172,"remaining_time":0.1455267149},
{"learn":[7.316897664],"iteration":837,"passed_time":0.7482146047,"remaining_time":0.1446429188},
{"learn":[7.309495788],"iteration":838,"passed_time":0.7490338656,"remaining_time":0.1437359384},
{"learn":[7.300477757],"iteration":839,"passed_time":0.7497096662,"remaining_time":0.1428018412},
{"learn":[7.288445402],"iteration":840,"passed_time":0.7503986337,"remaining_time":0.1418708475},
{"learn":[7.282149694],"iteration":841,"passed_time":0.7510824761,"remaining_time":0.140939467},
{"learn":[7.274901927],"iteration":842,"passed_time":0.7519136122,"remaining_time":0.1400361057},
{"learn":[7.269044045],"iteration":843,"passed_time":0.7530140434,"remaining_time":0.1391826905},
{"learn":[7.263514993],"iteration":844,"passed_time":0.7538434295,"remaining_time":0.1382789723},
{"learn":[7.256526168],"iteration":845,"passed_time":0.7549818196,"remaining_time":0.1374316787},
{"learn":[7.249197584],"iteration":846,"passed_time":0.7558582896,"remaining_time":0.1365363852},
{"learn":[7.244043048],"iteration":847,"passed_time":0.7566965507,"remaining_time":0.1356342874},
{"learn":[7.241560806],"iteration":848,"passed_time":0.757472811,"remaining_time":0.1347213127},
{"learn":[7.235707598],"iteration":849,"passed_time":0.7582609465,"remaining_time":0.1338107553},
{"learn":[7.228407471],"iteration":850,"passed_time":0.7593386691,"remaining_time":0.1329511888},
{"learn":[7.22255041],"iteration":851,"passed_time":0.760583769,"remaining_time":0.1321201852},
{"learn":[7.217531193],"iteration":852,"passed_time":0.7615093646,"remaining_time":0.1312331496},
{"learn":[7.211921558],"iteration":853,"passed_time":0.7622125406,"remaining_time":0.1303079987},
{"learn":[7.208083735],"iteration":854,"passed_time":0.7628958414,"remaining_time":0.1293799965},
{"learn":[7.204694472],"iteration":855,"passed_time":0.7638799378,"remaining_time":0.1285031671},
{"learn":[7.200927198],"iteration":856,"passed_time":0.7647151155,"remaining_time":0.1276012386},
{"learn":[7.194481895],"iteration":857,"passed_time":0.7654315,"remaining_time":0.1266798054},
{"learn":[7.191165574],"iteration":858,"passed_time":0.7661416761,"remaining_time":0.1257578304},
{"learn":[7.181721039],"iteration":859,"passed_time":0.7668723942,"remaining_time":0.1248396921},
{"learn":[7.170102443],"iteration":860,"passed_time":0.7676603213,"remaining_time":0.1239312249},
{"learn":[7.167940929],"iteration":861,"passed_time":0.7683364136,"remaining_time":0.1230051335},
{"learn":[7.160621394],"iteration":862,"passed_time":0.7690914653,"remaining_time":0.1220921561},
{"learn":[7.15427608],"iteration":863,"passed_time":0.769844642,"remaining_time":0.1211792492},
{"learn":[7.150447032],"iteration":864,"passed_time":0.7706107355,"remaining_time":0.1202687275},
{"learn":[7.142881155],"iteration":865,"passed_time":0.7713370785,"remaining_time":0.1193523886},
{"learn":[7.135593905],"iteration":866,"passed_time":0.7721715062,"remaining_time":0.1184530684},
{"learn":[7.127413629],"iteration":867,"passed_time":0.772880349,"remaining_time":0.1175347996},
{"learn":[7.122182152],"iteration":868,"passed_time":0.7736763179,"remaining_time":0.1166301469},
{"learn":[7.117167824],"iteration":869,"passed_time":0.7743819523,"remaining_time":0.1157122457},
{"learn":[7.109348379],"iteration":870,"passed_time":0.775217005,"remaining_time":0.1148139996},
{"learn":[7.10530735],"iteration":871,"passed_time":0.776097475,"remaining_time":0.1139225651},
{"learn":[7.099160926],"iteration":872,"passed_time":0.7768419849,"remaining_time":0.113011377},
{"learn":[7.094338492],"iteration":873,"passed_time":0.7774971603,"remaining_time":0.1120876913},
{"learn":[7.092489148],"iteration":874,"passed_time":0.7783251296,"remaining_time":0.1111893042},
{"learn":[7.081917606],"iteration":875,"passed_time":0.7790236389,"remaining_time":0.1102727525},
{"learn":[7.077628173],"iteration":876,"passed_time":0.7798935255,"remaining_time":0.1093807339},
{"learn":[7.072407234],"iteration":877,"passed_time":0.7807055363,"remaining_time":0.1084807237},
{"learn":[7.068806024],"iteration":878,"passed_time":0.7814339209,"remaining_time":0.1075694021},
{"learn":[7.061386403],"iteration":879,"passed_time":0.7821505971,"remaining_time":0.1066568996},
{"learn":[7.055831891],"iteration":880,"passed_time":0.7828303978,"remaining_time":0.1057398608},
{"learn":[7.05224484],"iteration":881,"passed_time":0.783525657,"remaining_time":0.104825428},
{"learn":[7.046248567],"iteration":882,"passed_time":0.7841952493,"remaining_time":0.1039080908},
{"learn":[7.041725143],"iteration":883,"passed_time":0.7848677999,"remaining_time":0.1029917022},
{"learn":[7.034346089],"iteration":884,"passed_time":0.7858518129,"remaining_time":0.1021163373},
{"learn":[7.028439532],"iteration":885,"passed_time":0.7866826156,"remaining_time":0.1012210138},
{"learn":[7.026203719],"iteration":886,"passed_time":0.7874103753,"remaining_time":0.1003127085},
{"learn":[7.020186402],"iteration":887,"passed_time":0.7881595519,"remaining_time":0.09940751105},
{"learn":[7.010979927],"iteration":888,"passed_time":0.7888660196,"remaining_time":0.09849733204},
{"learn":[7.004317112],"iteration":889,"passed_time":0.7895574455,"remaining_time":0.09758575169},
{"learn":[6.997936485],"iteration":890,"passed_time":0.7904517907,"remaining_time":0.09669948955},
{"learn":[6.990739166],"iteration":891,"passed_time":0.7914071367,"remaining_time":0.09582059503},
{"learn":[6.989789021],"iteration":892,"passed_time":0.7921598551,"remaining_time":0.09491725027},
{"learn":[6.97728336],"iteration":893,"passed_time":0.7929682825,"remaining_time":0.09402084781},
{"learn":[6.974224474],"iteration":894,"passed_time":0.7936419164,"remaining_time":0.09310882818},
{"learn":[6.967284092],"iteration":895,"passed_time":0.7943695927,"remaining_time":0.09220361344},
{"learn":[6.960048227],"iteration":896,"passed_time":0.7951286862,"remaining_time":0.09130240209},
{"learn":[6.952939606],"iteration":897,"passed_time":0.7959626139,"remaining_time":0.09041000737},
{"learn":[6.944908905],"iteration":898,"passed_time":0.796721624,"remaining_time":0.08950932594},
{"learn":[6.941370363],"iteration":899,"passed_time":0.7977655129,"remaining_time":0.08864061254},
{"learn":[6.934248821],"iteration":900,"passed_time":0.7985656485,"remaining_time":0.08774472719},
{"learn":[6.927259977],"iteration":901,"passed_time":0.7993364504,"remaining_time":0.08684586711},
{"learn":[6.920521972],"iteration":902,"passed_time":0.8000668768,"remaining_time":0.08594295354},
{"learn":[6.915407308],"iteration":903,"passed_time":0.800761261,"remaining_time":0.08503659409},
{"learn":[6.909039994],"iteration":904,"passed_time":0.8014340616,"remaining_time":0.0841284374},
{"learn":[6.905063526],"iteration":905,"passed_time":0.8021458627,"remaining_time":0.08322484668},
{"learn":[6.90166216],"iteration":906,"passed_time":0.8028544971,"remaining_time":0.08232135417},
{"learn":[6.897696961],"iteration":907,"passed_time":0.8036036321,"remaining_time":0.08142239444},
{"learn":[6.892897756],"iteration":908,"passed_time":0.8043105998,"remaining_time":0.08051954299},
{"learn":[6.88681252],"iteration":909,"passed_time":0.805105902,"remaining_time":0.07962585844},
{"learn":[6.880851722],"iteration":910,"passed_time":0.8057949112,"remaining_time":0.07872200559},
{"learn":[6.878751534],"iteration":911,"passed_time":0.8066403391,"remaining_time":0.07783371693},
{"learn":[6.870103182],"iteration":912,"passed_time":0.8074564749,"remaining_time":0.07694273091},
{"learn":[6.866077096],"iteration":913,"passed_time":0.8086310322,"remaining_time":0.07608563322},
{"learn":[6.86451951],"iteration":914,"passed_time":0.80934625,"remaining_time":0.07518517077},
{"learn":[6.864017739],"iteration":915,"passed_time":0.8097438803,"remaining_time":0.07425598902},
{"learn":[6.858581261],"iteration":916,"passed_time":0.8105034737,"remaining_time":0.07336072881},
{"learn":[6.852732248],"iteration":917,"passed_time":0.8115385708,"remaining_time":0.07249037343},
{"learn":[6.849407745],"iteration":918,"passed_time":0.8123142061,"remaining_time":0.07159679074},
{"learn":[6.846130379],"iteration":919,"passed_time":0.8130723412,"remaining_time":0.07070194271},
{"learn":[6.838938695],"iteration":920,"passed_time":0.8138774352,"remaining_time":0.06981141952},
{"learn":[6.835194496],"iteration":921,"passed_time":0.814663154,"remaining_time":0.06891944253},
{"learn":[6.830597412],"iteration":922,"passed_time":0.8155850829,"remaining_time":0.06803905892},
{"learn":[6.830128483],"iteration":923,"passed_time":0.8163271761,"remaining_time":0.0671437937},
{"learn":[6.825898135],"iteration":924,"passed_time":0.8175073584,"remaining_time":0.06628438041},
{"learn":[6.821295258],"iteration":925,"passed_time":0.8189605444,"remaining_time":0.06544609102},
{"learn":[6.816856715],"iteration":926,"passed_time":0.820309229,"remaining_time":0.06459824565},
{"learn":[6.806178837],"iteration":927,"passed_time":0.8213838682,"remaining_time":0.06372805874},
{"learn":[6.801381331],"iteration":928,"passed_time":0.8222033791,"remaining_time":0.06283793317},
{"learn":[6.797721051],"iteration":929,"passed_time":0.8232509764,"remaining_time":0.06196512725},
{"learn":[6.791748848],"iteration":930,"passed_time":0.8240105281,"remaining_time":0.06107059768},
{"learn":[6.787396055],"iteration":931,"passed_time":0.8247669132,"remaining_time":0.06017612671},
{"learn":[6.780082559],"iteration":932,"passed_time":0.8256658001,"remaining_time":0.059292185},
{"learn":[6.768680697],"iteration":933,"passed_time":0.826333934,"remaining_time":0.0583919054},
{"learn":[6.767097241],"iteration":934,"passed_time":0.8270836523,"remaining_time":0.05749779401},
{"learn":[6.7648381],"iteration":935,"passed_time":0.8278094119,"remaining_time":0.05660235295},
{"learn":[6.760263983],"iteration":936,"passed_time":0.8286026308,"remaining_time":0.05571180975},
{"learn":[6.752961031],"iteration":937,"passed_time":0.8293294321,"remaining_time":0.054817084},
{"learn":[6.746775428],"iteration":938,"passed_time":0.8300489,"remaining_time":0.05392223951},
{"learn":[6.744033254],"iteration":939,"passed_time":0.8308404105,"remaining_time":0.05303236663},
{"learn":[6.74340206],"iteration":940,"passed_time":0.831506086,"remaining_time":0.05213481304},
{"learn":[6.739243436],"iteration":941,"passed_time":0.832206762,"remaining_time":0.05123990679},
{"learn":[6.733115477],"iteration":942,"passed_time":0.8329423551,"remaining_time":0.05034752305},
{"learn":[6.729466935],"iteration":943,"passed_time":0.8336462811,"remaining_time":0.04945359295},
{"learn":[6.725887101],"iteration":944,"passed_time":0.8343338319,"remaining_time":0.04855911191},
{"learn":[6.717637053],"iteration":945,"passed_time":0.8350495497,"remaining_time":0.0476666762},
{"learn":[6.715344444],"iteration":946,"passed_time":0.8357041834,"remaining_time":0.04677119506},
{"learn":[6.711577626],"iteration":947,"passed_time":0.836400651,"remaining_time":0.04587851672},
{"learn":[6.706240324],"iteration":948,"passed_time":0.8371038687,"remaining_time":0.04498661465},
{"learn":[6.698256171],"iteration":949,"passed_time":0.8377898361,"remaining_time":0.0440942019},
{"learn":[6.689823517],"iteration":950,"passed_time":0.8384531783,"remaining_time":0.04320105756},
{"learn":[6.686224048],"iteration":951,"passed_time":0.8395102757,"remaining_time":0.04232824919},
{"learn":[6.680408198],"iteration":952,"passed_time":0.8404278295,"remaining_time":0.04144817207},
{"learn":[6.676510583],"iteration":953,"passed_time":0.8411623393,"remaining_time":0.04055919036},
{"learn":[6.672383773],"iteration":954,"passed_time":0.8420380592,"remaining_time":0.03967718604},
{"learn":[6.666290972],"iteration":955,"passed_time":0.8433379515,"remaining_time":0.03881471743},
{"learn":[6.662303196],"iteration":956,"passed_time":0.8440648361,"remaining_time":0.03792558825},
{"learn":[6.657634373],"iteration":957,"passed_time":0.844784304,"remaining_time":0.03703647262},
{"learn":[6.65150612],"iteration":958,"passed_time":0.8454639381,"remaining_time":0.03614600778},
{"learn":[6.647300522],"iteration":959,"passed_time":0.8461705308,"remaining_time":0.03525710545},
{"learn":[6.64304655],"iteration":960,"passed_time":0.8469308742,"remaining_time":0.03437076389},
{"learn":[6.640409223],"iteration":961,"passed_time":0.8476885093,"remaining_time":0.03348457729},
{"learn":[6.635460211],"iteration":962,"passed_time":0.8484097689,"remaining_time":0.03259726007},
{"learn":[6.62817859],"iteration":963,"passed_time":0.8491068615,"remaining_time":0.03170938487},
{"learn":[6.623826648],"iteration":964,"passed_time":0.8497929122,"remaining_time":0.03082150459},
{"learn":[6.618430452],"iteration":965,"passed_time":0.8504897132,"remaining_time":0.02993442055},
{"learn":[6.616055501],"iteration":966,"passed_time":0.8511575137,"remaining_time":0.02904674038},
{"learn":[6.613831332],"iteration":967,"passed_time":0.8518632731,"remaining_time":0.02816076936},
{"learn":[6.608975736],"iteration":968,"passed_time":0.8525036149,"remaining_time":0.02727307746},
{"learn":[6.595904848],"iteration":969,"passed_time":0.8531961241,"remaining_time":0.02638750899},
{"learn":[6.590898628],"iteration":970,"passed_time":0.8539204671,"remaining_time":0.02550328892},
{"learn":[6.585534495],"iteration":971,"passed_time":0.8545842259,"remaining_time":0.0246176526},
{"learn":[6.581693881],"iteration":972,"passed_time":0.8552288594,"remaining_time":0.02373194163},
{"learn":[6.578458108],"iteration":973,"passed_time":0.8559591608,"remaining_time":0.02284901251},
{"learn":[6.574323936],"iteration":974,"passed_time":0.8566360865,"remaining_time":0.02196502786},
{"learn":[6.570704821],"iteration":975,"passed_time":0.8573087621,"remaining_time":0.021081363},
{"learn":[6.563526634],"iteration":976,"passed_time":0.8580343134,"remaining_time":0.02019937483},
{"learn":[6.561590829],"iteration":977,"passed_time":0.8587192391,"remaining_time":0.0193167927},
{"learn":[6.556785309],"iteration":978,"passed_time":0.8594193318,"remaining_time":0.0184349397},
{"learn":[6.555662927],"iteration":979,"passed_time":0.8601314245,"remaining_time":0.01755370254},
{"learn":[6.551685018],"iteration":980,"passed_time":0.8609068932,"remaining_time":0.01667403769},
{"learn":[6.546576166],"iteration":981,"passed_time":0.8615777771,"remaining_time":0.01579266801},
{"learn":[6.542967197],"iteration":982,"passed_time":0.86229762,"remaining_time":0.01491257329},
{"learn":[6.539380645],"iteration":983,"passed_time":0.8630072127,"remaining_time":0.01403263761},
{"learn":[6.535743987],"iteration":984,"passed_time":0.8636785967,"remaining_time":0.01315246594},
{"learn":[6.533627599],"iteration":985,"passed_time":0.8643108967,"remaining_time":0.01227216283},
{"learn":[6.531061697],"iteration":986,"passed_time":0.8649487802,"remaining_time":0.01139243581},
{"learn":[6.52500236],"iteration":987,"passed_time":0.8655956638,"remaining_time":0.01051330766},
{"learn":[6.519313097],"iteration":988,"passed_time":0.866261506,"remaining_time":0.009634860026},
{"learn":[6.512995815],"iteration":989,"passed_time":0.8669413067,"remaining_time":0.008756982896},
{"learn":[6.508492181],"iteration":990,"passed_time":0.8675741067,"remaining_time":0.007879078669},
{"learn":[6.502538742],"iteration":991,"passed_time":0.8682638242,"remaining_time":0.007002127615},
{"learn":[6.499558065],"iteration":992,"passed_time":0.8690115425,"remaining_time":0.006125962535},
{"learn":[6.495024923],"iteration":993,"passed_time":0.8697414272,"remaining_time":0.005249948253},
{"learn":[6.489419772],"iteration":994,"passed_time":0.8704092694,"remaining_time":0.004373915927},
{"learn":[6.480558194],"iteration":995,"passed_time":0.8711346124,"remaining_time":0.00349853258},
{"learn":[6.474458978],"iteration":996,"passed_time":0.8718871224,"remaining_time":0.002623531963},
{"learn":[6.467282549],"iteration":997,"passed_time":0.8729647617,"remaining_time":0.00174942838},
{"learn":[6.464025401],"iteration":998,"passed_time":0.8741528191,"remaining_time":0.000875027847},
{"learn":[6.460657147],"iteration":999,"passed_time":0.8748936623,"remaining_time":0}
]}